Workbook

Sheet Sales_by Inv No & by custom WSK
A3: Sum of Sales Amount | D3: Year (Sales) | E3: Period (Sales) | Z3: Sum of Sales Amount | AC3: Year (Sales) | AD3: Period (Sales)
D4: 2022 | P4: 2022 Total | Q4: Grand Total | AC4: 2022 | AK4: 2022 Total | AL4: Grand Total
A5: Customer Name | B5: Invoice No | C5: Invoice Date | D5: 6 | E5: 7 | F5: 8 | G5: 9 | H5: 10 | I5: 11 | J5: 12 | K5: 1 | L5: 2 | M5: 3 | N5: 4 | O5: 5 | Z5: Customer Name | AA5: Invoice No | AB5: Invoice Date | AC5: 6 | AD5: 7 | AE5: 8 | AF5: 1 | AG5: 2 | AH5: 3 | AI5: 4 | AJ5: 5
A6: WSK Tanks Sdn Bhd | B6: INV00000182 | C6: 44564 | K6: 8273 | P6: 8273 | Q6: 8273 | Z6: Yew Seng Gardening Supply Sdn Bhd | AA6: INV00000187 | AB6: 44572 | AF6: 15346 | AK6: 15346 | AL6: 15346
B7: INV00000184 | C7: 44568 | K7: 1233 | P7: 1233 | Q7: 1233 | AA7: INV00000195 | AB7: 44585 | AF7: 13474 | AK7: 13474 | AL7: 13474
B8: INV00000185 | C8: 44569 | K8: 7377 | P8: 7377 | Q8: 7377 | AA8: INV00000200 | AB8: 44609 | AG8: 14395 | AK8: 14395 | AL8: 14395
B9: INV00000189 | C9: 44574 | K9: 28549 | P9: 28549 | Q9: 28549 | AA9: INV00000211 | AB9: 44628 | AH9: 15280 | AK9: 15280 | AL9: 15280
B10: INV00000193 | C10: 44579 | K10: 11502 | P10: 11502 | Q10: 11502 | AA10: INV00000217 | AB10: 44635 | AH10: 14185 | AK10: 14185 | AL10: 14185
B11: INV00000206 | C11: 44616 | L11: 7961 | P11: 7961 | Q11: 7961 | AA11: INV00000251 | AB11: 44678 | AI11: 11160 | AK11: 11160 | AL11: 11160
B12: INV00000207 | C12: 44618 | L12: 2678 | P12: 2678 | Q12: 2678 | AA12: INV00000272 | AB12: 44704 | AJ12: 14715 | AK12: 14715 | AL12: 14715
B13: INV00000216 | C13: 44634 | M13: 3029 | P13: 3029 | Q13: 3029 | AA13: INV00000282 | AB13: 44721 | AC13: 12690 | AK13: 12690 | AL13: 12690
B14: INV00000218 | C14: 44635 | M14: 11425 | P14: 11425 | Q14: 11425 | AA14: INV00000294 | AB14: 44741 | AC14: 18515 | AK14: 18515 | AL14: 18515
B15: INV00000220 | C15: 44638 | M15: 9888 | P15: 9888 | Q15: 9888 | AA15: INV00000303 | AB15: 44768 | AD15: 13445 | AK15: 13445 | AL15: 13445
B16: INV00000223 | C16: 44643 | M16: 8819 | P16: 8819 | Q16: 8819 | AA16: INV00000318 | AB16: 44798 | AE16: 15671 | AK16: 15671 | AL16: 15671
B17: INV00000224 | C17: 44645 | M17: 14422 | P17: 14422 | Q17: 14422 | Z17: Yew Seng Gardening Supply Sdn Bhd Total | AC17: 31205 | AD17: 13445 | AE17: 15671 | AF17: 28820 | AG17: 14395 | AH17: 29465 | AI17: 11160 | AJ17: 14715 | AK17: 158876 | AL17: 158876
B18: INV00000226 | C18: 44649 | M18: 7593 | P18: 7593 | Q18: 7593 | Z18: Grand Total | AC18: 31205 | AD18: 13445 | AE18: 15671 | AF18: 28820 | AG18: 14395 | AH18: 29465 | AI18: 11160 | AJ18: 14715 | AK18: 158876 | AL18: 158876
B19: INV00000229 | C19: 44652 | N19: 9157.5 | P19: 9157.5 | Q19: 9157.5
B20: INV00000231 | C20: 44656 | N20: 10497.5 | P20: 10497.5 | Q20: 10497.5
B21: INV00000235 | C21: 44660 | N21: 8569.5 | P21: 8569.5 | Q21: 8569.5
B22: INV00000239 | C22: 44664 | N22: 10975.5 | P22: 10975.5 | Q22: 10975.5
B23: INV00000242 | C23: 44667 | N23: 10103.5 | P23: 10103.5 | Q23: 10103.5
B24: INV00000244 | C24: 44670 | N24: 3076 | P24: 3076 | Q24: 3076
B25: INV00000249 | C25: 44674 | N25: 11151 | P25: 11151 | Q25: 11151
B26: INV00000253 | C26: 44679 | N26: 11858.5 | P26: 11858.5 | Q26: 11858.5
B27: INV00000256 | C27: 44681 | N27: 15244 | P27: 15244 | Q27: 15244
B28: INV00000257 | C28: 44687 | O28: 11530 | P28: 11530 | Q28: 11530
B29: INV00000259 | C29: 44688 | O29: 16245 | P29: 16245 | Q29: 16245
B30: INV00000265 | C30: 44695 | O30: 10369.5 | P30: 10369.5 | Q30: 10369.5
B31: INV00000267 | C31: 44699 | O31: 8417 | P31: 8417 | Q31: 8417
B32: INV00000269 | C32: 44701 | O32: 13110 | P32: 13110 | Q32: 13110
B33: INV00000271 | C33: 44702 | O33: 13110 | P33: 13110 | Q33: 13110
B34: INV00000273 | C34: 44704 | O34: 6750 | P34: 6750 | Q34: 6750
B35: INV00000276 | C35: 44706 | O35: 14068 | P35: 14068 | Q35: 14068
B36: INV00000278 | C36: 44714 | D36: 12427 | P36: 12427 | Q36: 12427
B37: INV00000280 | C37: 44716 | D37: 9000 | P37: 9000 | Q37: 9000
B38: INV00000285 | C38: 44723 | D38: 4950 | P38: 4950 | Q38: 4950
B39: INV00000289 | C39: 44730 | D39: 4431.5 | P39: 4431.5 | Q39: 4431.5
B40: INV00000292 | C40: 44736 | D40: 5889 | P40: 5889 | Q40: 5889
B41: INV00000297 | C41: 44756 | E41: 12855.5 | P41: 12855.5 | Q41: 12855.5
B42: INV00000299 | C42: 44760 | E42: 9153 | P42: 9153 | Q42: 9153
B43: INV00000300 | C43: 44762 | E43: 925.5 | P43: 925.5 | Q43: 925.5
B44: INV00000301 | C44: 44765 | E44: 6625 | P44: 6625 | Q44: 6625
B45: INV00000307 | C45: 44779 | F45: 5268.6 | P45: 5268.6 | Q45: 5268.6
B46: INV00000310 | C46: 44785 | F46: 4312.5 | P46: 4312.5 | Q46: 4312.5
B47: INV00000316 | C47: 44796 | F47: 6838.5 | P47: 6838.5 | Q47: 6838.5
B48: INV00000321 | C48: 44806 | G48: 9343.9 | P48: 9343.9 | Q48: 9343.9
B49: INV00000323 | C49: 44810 | G49: 11453.6 | P49: 11453.6 | Q49: 11453.6
B50: INV00000325 | C50: 44813 | G50: 1914 | P50: 1914 | Q50: 1914
B51: INV00000327 | C51: 44817 | G51: 13163 | P51: 13163 | Q51: 13163
B52: INV00000328 | C52: 44817 | G52: 11823 | P52: 11823 | Q52: 11823
B53: INV00000339 | C53: 3/10/2022 | H53: 48172.5 | P53: 48172.5 | Q53: 48172.5
B54: INV00000345 | C54: 44847 | H54: 10166.3 | P54: 10166.3 | Q54: 10166.3
B55: INV00000353 | C55: 44856 | H55: 7590.5 | P55: 7590.5 | Q55: 7590.5
B56: INV00000355 | C56: 44861 | H56: 250 | P56: 250 | Q56: 250
B57: INV00000356 | C57: 44865 | H57: 47685 | P57: 47685 | Q57: 47685
B58: INV00000361 | C58: 44869 | I58: 403.8 | P58: 403.8 | Q58: 403.8
B59: INV00000366 | C59: 44876 | I59: 14886.5 | P59: 14886.5 | Q59: 14886.5
B60: INV00000372 | C60: 22/11/2022 | I60: 17236.6 | P60: 17236.6 | Q60: 17236.6
B61: INV00000379 | C61: 44897 | J61: 4489 | P61: 4489 | Q61: 4489
B62: INV00000380 | C62: 44897 | J62: 3915 | P62: 3915 | Q62: 3915
B63: INV00000382 | C63: 44898 | J63: 7395.5 | P63: 7395.5 | Q63: 7395.5
B64: INV00000386 | C64: 44904 | J64: 49088.1 | P64: 49088.1 | Q64: 49088.1
B65: INV00000389 | C65: 44917 | J65: 47686.5 | P65: 47686.5 | Q65: 47686.5
B66: INV00000395 | C66: 44923 | J66: 1008 | P66: 1008 | Q66: 1008
B67: INV00000396 | C67: 44925 | J67: 21740.5 | P67: 21740.5 | Q67: 21740.5
A68: WSK Tanks Sdn Bhd Total | D68: 36697.5 | E68: 29559 | F68: 16419.6 | G68: 47697.5 | H68: 113864.3 | I68: 32526.9 | J68: 135322.6 | K68: 56934 | L68: 10639 | M68: 55176 | N68: 90633 | O68: 93599.5 | P68: 719068.9 | Q68: 719068.9
A69: Grand Total | D69: 36697.5 | E69: 29559 | F69: 16419.6 | G69: 47697.5 | H69: 113864.3 | I69: 32526.9 | J69: 135322.6 | K69: 56934 | L69: 10639 | M69: 55176 | N69: 90633 | O69: 93599.5 | P69: 719068.9 | Q69: 719068.9

Sheet Customer Aging
A1: Customer Aging
A2: Month : As of July 2025
A4: Sum of Outstanding | B4: Term | W4: Sum of Outstanding | AB4: Term | AR4: Sum of Outstanding | AU4: Term
A5: Customer Name | B5: 0 | C5: 45 | D5: 60 | E5: 120 | F5: #N/A | G5: 30 | H5: Grand Total | W5: Customer Name | X5: Year (Due) | Y5: Period (Due) | Z5: Invoice Date | AA5: Invoice No | AB5: 0 | AC5: 45 | AD5: 60 | AE5: 120 | AF5: #N/A | AG5: 30 | AH5: Grand Total | AR5: Customer Name | AS5: Year (Due) | AT5: Period (Due) | AU5: 0 | AV5: 45 | AW5: 60 | AX5: 120 | AY5: #N/A | AZ5: 30 | BA5: Grand Total
A6: Artscene Creative | B6: 0 | H6: 0 | W6: Artscene Creative | X6: 2020 | Y6: 8 | Z6: 44053 | AA6: INV2020/00000012 | AB6: 0 | AH6: 0 | AR6: Artscene Creative | AS6: 2020 | AT6: 8 | AU6: 0 | BA6: 0
A7: Chin Fibreglass (M) Sdn Bhd | B7: 0 | H7: 0 | Y7: 10 | Z7: 44109 | AA7: INV2020/00000033 | AB7: 0 | AH7: 0 | AT7: 10 | AU7: 0 | BA7: 0
A8: JMC Steel Engineering Sdn Bhd | D8: 0 | H8: 0 | Z8: 44123 | AA8: INV2020/00000042 | AB8: 0 | AH8: 0 | AT8: 11 | AU8: 0 | BA8: 0
A9: Kelnico Marketing | B9: 0 | H9: 0 | Z9: 44125 | AA9: INV2020/00000043 | AB9: 0 | AH9: 0 | AS9: 2021 | AT9: 2 | AU9: 0 | BA9: 0
A10: Pandian Art Gallery Manufacturing | C10: 1277.5 | H10: 1277.5 | Z10: 44135 | AA10: INV2020/00000047 | AB10: 0 | AH10: 0 | AT10: 5 | AU10: 0 | BA10: 0
A11: Perniagaan Fibra Sahih | B11: 0.2 | H11: 0.2 | Y11: 11 | Z11: 44145 | AA11: INV2020/00000050 | AB11: 0 | AH11: 0 | AT11: 9 | AU11: 0 | BA11: 0
A12: Siew Min Lorry Sdn Bhd | E12: 0 | H12: 0 | Z12: 44158 | AA12: INV2020/00000056 | AB12: 0 | AH12: 0 | AT12: 10 | AU12: 0 | BA12: 0
A13: Sley | B13: 0 | H13: 0 | X13: 2021 | Y13: 2 | Z13: 44229 | AA13: INV2020/00000078 | AB13: 0 | AH13: 0 | AT13: 11 | AU13: 0 | BA13: 0
A14: Wonderland Design Productions Studio | B14: 0 | H14: 0 | Z14: 44244 | AA14: INV2020/00000081 | AB14: 0 | AH14: 0 | AS14: 2024 | AT14: 10 | AU14: 0 | BA14: 0
A15: Yew Seng Gardening Supply Sdn Bhd | E15: 52482.9 | H15: 52482.9 | Y15: 5 | Z15: 44322 | AA15: INV00000103 | AB15: 0 | AH15: 0 | AT15: 11 | AU15: 0 | BA15: 0
A16: JT Johan Sdn Bhd | B16: 0 | H16: 0 | Z16: 44335 | AA16: INV00000105 | AB16: 0 | AH16: 0 | AR16: Artscene Creative Total | AU16: 0 | BA16: 0
A17: Cash - Muhammad Syahin Bin | F17: 0 | H17: 0 | Z17: 44341 | AA17: INV00000107 | AB17: 0 | AH17: 0 | AR17: Chin Fibreglass (M) Sdn Bhd | AS17: 2020 | AT17: 8 | AU17: 0 | BA17: 0
A18: Cash - PMC | F18: 0 | H18: 0 | Y18: 9 | Z18: 44440 | AA18: INV00000113 | AB18: 0 | AH18: 0 | AT18: 10 | AU18: 0 | BA18: 0
A19: IK Fibre Glass Enterprise | B19: 0 | H19: 0 | AA19: INV00000114 | AB19: 0 | AH19: 0 | AR19: Chin Fibreglass (M) Sdn Bhd Total | AU19: 0 | BA19: 0
A20: S&J Business Solutions | B20: 0 | H20: 0 | Z20: 44467 | AA20: INV00000122 | AB20: 0 | AH20: 0 | AR20: JMC Steel Engineering Sdn Bhd | AS20: 2020 | AT20: 10 | AW20: 0 | BA20: 0
A21: Win Fiber Sdn Bhd | B21: 0 | H21: 0 | Y21: 10 | Z21: 44484 | AA21: INV00000137 | AB21: 0 | AH21: 0 | AS21: 2021 | AT21: 1 | AW21: 0 | BA21: 0
A22: Living Divani (M) Sdn Bhd | B22: 0 | H22: 0 | Y22: 11 | Z22: 44501 | AA22: INV00000150 | AB22: 0 | AH22: 0 | AT22: 5 | AW22: 0 | BA22: 0
A23: Desuki Affela Empire Enterprise | B23: 96862.3 | H23: 96862.3 | X23: 2024 | Y23: 10 | Z23: 45582 | AA23: INV00001000 | AB23: 0 | AH23: 0 | AT23: 6 | AW23: 0 | BA23: 0
A24: WSK Tanks Sdn Bhd | B24: 4.5474735e-13 | H24: 4.5474735e-13 | Y24: 11 | Z24: 45600 | AA24: INV00001020 | AB24: 0 | AH24: 0 | AT24: 7 | AW24: 0 | BA24: 0
A25: Cash - En Mat | F25: 0 | H25: 0 | W25: Artscene Creative Total | AB25: 0 | AH25: 0 | AT25: 12 | AW25: 0 | BA25: 0
A26: KT Profesional Fiber | B26: 28583.6 | H26: 28583.6 | W26: Chin Fibreglass (M) Sdn Bhd | X26: 2020 | Y26: 8 | Z26: 44065 | AA26: INV2020/00000018 | AB26: 0 | AH26: 0 | AS26: 2022 | AT26: 6 | AW26: 0 | BA26: 0
A27: SF Engineering Solution | B27: 514.2 | H27: 514.2 | Y27: 10 | Z27: 44118 | AA27: INV2020/00000038 | AB27: 0 | AH27: 0 | AT27: 7 | AW27: 0 | BA27: 0
A28: Bestway Engineering Solutions | B28: 0 | H28: 0 | Z28: 44123 | AA28: INV2020/00000038 | AB28: 0 | AH28: 0 | AT28: 8 | AW28: 0 | BA28: 0
A29: LLL Automotive Sdn Bhd | B29: 0 | H29: 0 | W29: Chin Fibreglass (M) Sdn Bhd Total | AB29: 0 | AH29: 0 | AT29: 9 | AW29: 0 | BA29: 0
A30: Worldwide Competence Sdn Bhd | B30: 0 | H30: 0 | W30: JMC Steel Engineering Sdn Bhd | X30: 2020 | Y30: 10 | Z30: 44068 | AA30: INV2020/00000021 | AD30: 0 | AH30: 0 | AT30: 10 | AW30: 0 | BA30: 0
A31: Megapower Service | B31: 0 | H31: 0 | X31: 2021 | Y31: 1 | Z31: 44146 | AA31: INV2020/00000051 | AD31: 0 | AH31: 0 | AT31: 11 | AW31: 0 | BA31: 0
A32: Transform Star Sdn Bhd | B32: 33600.6 | H32: 33600.6 | Z32: 44163 | AA32: INV2020/00000060 | AD32: 0 | AH32: 0 | AT32: 12 | AW32: 0 | BA32: 0
A33: Cash - Vinz Yew Kok Wah | B33: 0 | H33: 0 | Y33: 5 | Z33: 44266 | AA33: INV00000088 | AD33: 0 | AH33: 0 | AT33: 4 | AW33: 0 | BA33: 0
A34: CANCELLED INVOICE | F34: 0 | H34: 0 | Z34: 44279 | AA34: INV00000091 | AD34: 0 | AH34: 0 | AS34: 2023 | AT34: 1 | AW34: 0 | BA34: 0
A35: Cash - Big Jackfruit Trading | B35: 0 | H35: 0 | Y35: 6 | Z35: 44313 | AA35: INV00000100 | AD35: 0 | AH35: 0 | AT35: 2 | AW35: 0 | BA35: 0
A36: Hai Kee Hung Sdn Bhd | B36: 0 | H36: 0 | Y36: 7 | Z36: 44348 | AA36: INV00000109 | AD36: 0 | AH36: 0 | AT36: 3 | AW36: 0 | BA36: 0
A37: Cash - Zaina | B37: 0 | H37: 0 | AA37: INV00000110 | AD37: 0 | AH37: 0 | AT37: 5 | AW37: 0 | BA37: 0
A38: Cash - Zaidi | B38: 0 | H38: 0 | Y38: 12 | Z38: 44483 | AA38: INV00000135 | AD38: 0 | AH38: 0 | AT38: 6 | AW38: 0 | BA38: 0
A39: Cash - ZTY Fibre | B39: 2576.3 | H39: 2576.3 | X39: 2022 | Y39: 6 | Z39: 44660 | AA39: INV00000234 | AD39: 0 | AH39: 0 | AT39: 7 | AW39: 0 | BA39: 0
A40: Cash - MLGaia Enterprise | B40: 0 | H40: 0 | Y40: 7 | Z40: 44691 | AA40: INV00000260 | AD40: 0 | AH40: 0 | AT40: 8 | AW40: 0 | BA40: 0
A41: Choi Fook Sing Enterprise Sdn Bhd | B41: 0 | H41: 0 | Y41: 8 | Z41: 44726 | AA41: INV00000287 | AD41: 0 | AH41: 0 | AT41: 9 | AW41: 0 | BA41: 0
A42: Suntruck Sdn Bhd | G42: 18660 | H42: 18660 | Z42: 44743 | AA42: INV00000295 | AD42: 0 | AH42: 0 | AT42: 10 | AW42: 0 | BA42: 0
A43: WSA Engineering Sdn Bhd | B43: 0 | H43: 0 | Y43: 9 | Z43: 44771 | AA43: INV00000305 | AD43: 0 | AH43: 0 | AT43: 11 | AW43: 0 | BA43: 0
A44: Cash - PMC Sdn Bhd | B44: 0 | H44: 0 | Y44: 10 | Z44: 44796 | AA44: INV00000317 | AD44: 0 | AH44: 0 | AT44: 12 | AW44: 0 | BA44: 0
A45: Aumada Energy & Technologies (M) Sdn Bhd | B45: 0 | H45: 0 | Y45: 11 | Z45: 5/9/2022 | AA45: INV00000322 | AD45: 0 | AH45: 0 | AS45: 2024 | AT45: 2 | AW45: 0 | BA45: 0
A46: Bestway Bina Sdn Bhd | B46: 0 | H46: 0 | Y46: 12 | Z46: 44852 | AA46: INV00000350 | AD46: 0 | AH46: 0 | AT46: 3 | AW46: 0 | BA46: 0
A47: Dynamic Builders Trading | B47: 0 | H47: 0 | Y47: 4 | Z47: 44610 | AA47: INV00000201 | AD47: 0 | AH47: 0 | AT47: 5 | AW47: 0 | BA47: 0
A48: Airebus Sdn Bhd | B48: 0 | H48: 0 | X48: 2023 | Y48: 1 | Z48: 44868 | AA48: INV00000360 | AD48: 0 | AH48: 0 | AT48: 6 | AW48: 0 | BA48: 0
A49: Welltech (M) Sdn Bhd | B49: 522339.3 | H49: 522339.3 | Y49: 2 | Z49: 44898 | AA49: INV00000381 | AD49: 0 | AH49: 0 | AT49: 8 | AW49: 0 | BA49: 0
A50: RBD World Wide Sdn Bhd | B50: 0 | H50: 0 | Y50: 3 | Z50: 44953 | AA50: INV00000417 | AD50: 0 | AH50: 0 | AT50: 9 | AW50: 0 | BA50: 0
A51: Kelnico Sdn Bhd | B51: 0 | H51: 0 | Y51: 5 | Z51: 14/3/2023 | AA51: INV00000463 | AD51: 0 | AH51: 0 | AT51: 4 | AW51: 0 | BA51: 0
A52: Berkat Fibreglass | B52: 0 | H52: 0 | Y52: 6 | Z52: 6/4/2023 | AA52: INV00000486 | AD52: 0 | AH52: 0 | AR52: JMC Steel Engineering Sdn Bhd Total | AW52: 0 | BA52: 0
A53: KAD Builders Sdn Bhd | B53: 0 | H53: 0 | Z53: 19/4/2023 | AA53: INV00000499 | AD53: 0 | AH53: 0 | AR53: Kelnico Marketing | AS53: 2020 | AT53: 6 | AU53: 0 | BA53: 0
A54: Cash - Encik Mohammad Mongal | B54: 0 | H54: 0 | Y54: 7 | Z54: 45054 | AA54: INV00000513 | AD54: 0 | AH54: 0 | AT54: 7 | AU54: 0 | BA54: 0
A55: YL Professional Fiber Trading | B55: 2360 | H55: 2360 | Z55: 45072 | AA55: INV00000531 | AD55: 0 | AH55: 0 | AT55: 8 | AU55: 0 | BA55: 0
A56: DOB Engineering Solutions | B56: 18972.5 | H56: 18972.5 | Y56: 8 | Z56: 1/7/2023 | AA56: INV00000562 | AD56: 0 | AH56: 0 | AT56: 9 | AU56: 0 | BA56: 0
A57: Cash - Mr Wong | B57: 0 | H57: 0 | Y57: 9 | Z57: 45139 | AA57: INV00000589 | AD57: 0 | AH57: 0 | AT57: 10 | AU57: 0 | BA57: 0
A58: Cash - Shikh House of Design | B58: 0 | H58: 0 | Y58: 10 | Z58: 45147 | AA58: INV00000600 | AD58: 0 | AH58: 0 | AT58: 11 | AU58: 0 | BA58: 0
A59: Cash - Hamdan | B59: 0 | H59: 0 | Y59: 11 | Z59: 45177 | AA59: INV00000635 | AD59: 0 | AH59: 0 | AT59: 12 | AU59: 0 | BA59: 0
A60: Cash - Encik Razzak | B60: 0.5 | H60: 0.5 | Y60: 12 | Z60: 14/10/2023 | AA60: INV00000676 | AD60: 0 | AH60: 0 | AS60: 2021 | AT60: 1 | AU60: 0 | BA60: 0
A61: Cash - Jamid | B61: 515 | H61: 515 | Z61: 45218 | AA61: INV00000681 | AD61: 0 | AH61: 0 | AT61: 2 | AU61: 0 | BA61: 0
A62: Cash - Encik Aziz (Shikh House of Design) | B62: 0 | H62: 0 | X62: 2024 | Y62: 2 | Z62: 45273 | AA62: INV00000738 | AD62: 0 | AH62: 0 | AT62: 5 | AU62: 0 | BA62: 0
A63: Cash - Encik Aziz (Sg Lang Marine Ventures) | B63: 0 | H63: 0 | Y63: 3 | Z63: 45299 | AA63: INV00000769 | AD63: 0 | AH63: 0 | AT63: 9 | AU63: 0 | BA63: 0
A64: Cash - Encik Aziz | F64: 0 | H64: 0 | Y64: 5 | Z64: 45355 | AA64: INV00000819 | AD64: 0 | AH64: 0 | AT64: 10 | AU64: 0 | BA64: 0
A65: Cash Mr Tan | B65: 0 | H65: 0 | Y65: 6 | Z65: 45387 | AA65: INV00000843 | AD65: 0 | AH65: 0 | AT65: 12 | AU65: 0 | BA65: 0
A66: Cash - Shermark Resources | B66: 0 | H66: 0 | Z66: 45390 | AA66: INV00000844 | AD66: 0 | AH66: 0 | AT66: 4 | AU66: 0 | BA66: 0
A67: Cash - Kevin Wong | B67: 0 | H67: 0 | Z67: 45411 | AA67: INV00000858 | AD67: 0 | AH67: 0 | AS67: 2019 | AT67: 12 | AU67: 0 | BA67: 0
A68: Kai Chuan Fibreglass | B68: 0 | H68: 0 | Y68: 8 | Z68: 45468 | AA68: INV00000901 | AD68: 0 | AH68: 0 | AS68: 2022 | AT68: 3 | AU68: 0 | BA68: 0
A69: GK SHAANAZ ENTERPRISE | B69: 3923.7 | H69: 3923.7 | Y69: 9 | Z69: 45485 | AA69: INV00000918 | AD69: 0 | AH69: 0 | AT69: 6 | AU69: 0 | BA69: 0
A70: Protech Master Coach Sdn Bhd | B70: 0.5 | H70: 0.5 | Z70: 45496 | AA70: INV00000925 | AD70: 0 | AH70: 0 | AT70: 7 | AU70: 0 | BA70: 0
A71: Pioneer Coachbuilders Sdn Bhd | B71: 0 | H71: 0 | Y71: 4 | Z71: 45344 | AA71: INV00000808 | AD71: 0 | AH71: 0 | AT71: 8 | AU71: 0 | BA71: 0
A72: SK Setia Enterprise | B72: 0 | H72: 0 | W72: JMC Steel Engineering Sdn Bhd Total | AD72: 0 | AH72: 0 | AT72: 9 | AU72: 0 | BA72: 0
A73: Grand Total | B73: 710248.7 | C73: 1277.5 | D73: 0 | E73: 52482.9 | F73: 0 | G73: 18660 | H73: 782669.1 | W73: Kelnico Marketing | X73: 2020 | Y73: 6 | Z73: 43984 | AA73: INV2020/00000002 | AB73: 0 | AH73: 0 | AT73: 10 | AU73: 0 | BA73: 0
Z74: 43999 | AA74: INV2020/00000004 | AB74: 0 | AH74: 0 | AT74: 11 | AU74: 0 | BA74: 0
Y75: 7 | Z75: 44027 | AA75: INV2020/00000008 | AB75: 0 | AH75: 0 | AT75: 12 | AU75: 0 | BA75: 0
Y76: 8 | Z76: 44055 | AA76: INV2020/00000014 | AB76: 0 | AH76: 0 | AT76: 4 | AU76: 0 | BA76: 0
Z77: 44056 | AA77: INV2020/00000015 | AB77: 0 | AH77: 0 | AS77: 2023 | AT77: 1 | AU77: 0 | BA77: 0
Z78: 44068 | AA78: INV2020/00000022 | AB78: 0 | AH78: 0 | AT78: 3 | AU78: 0 | BA78: 0
Y79: 9 | Z79: 44076 | AA79: INV2020/00000025 | AB79: 0 | AH79: 0 | AT79: 5 | AU79: 0 | BA79: 0
Z80: 44079 | AA80: INV2020/00000026 | AB80: 0 | AH80: 0 | AT80: 4 | AU80: 0 | BA80: 0
Z81: 44091 | AA81: INV2020/00000028 | AB81: 0 | AH81: 0 | AR81: Kelnico Marketing Total | AU81: 0 | BA81: 0
Z82: 44097 | AA82: INV2020/00000031 | AB82: 0 | AH82: 0 | AR82: Pandian Art Gallery Manufacturing | AS82: 2020 | AT82: 8 | AV82: 0 | BA82: 0
Z83: 44100 | AA83: INV2020/00000032 | AB83: 0 | AH83: 0 | AT83: 9 | AV83: 0 | BA83: 0
Y84: 10 | Z84: 44116 | AA84: INV2020/00000037 | AB84: 0 | AH84: 0 | AT84: 10 | AV84: 0 | BA84: 0
Z85: 44123 | AA85: INV2020/00000041 | AB85: 0 | AH85: 0 | AT85: 11 | AV85: 0 | BA85: 0
Z86: 44135 | AA86: INV2020/00000046 | AB86: 0 | AH86: 0 | AT86: 12 | AV86: 0 | BA86: 0
Y87: 11 | Z87: 44145 | AA87: INV2020/00000049 | AB87: 0 | AH87: 0 | AS87: 2021 | AT87: 1 | AV87: 0 | BA87: 0
Z88: 44153 | AA88: INV2020/00000052 | AB88: 0 | AH88: 0 | AT88: 2 | AV88: 0 | BA88: 0
Z89: 44159 | AA89: INV2020/00000053 | AB89: 0 | AH89: 0 | AT89: 3 | AV89: 0 | BA89: 0
Z90: 44162 | AA90: INV2020/00000059 | AB90: 0 | AH90: 0 | AT90: 5 | AV90: 0 | BA90: 0
Y91: 12 | Z91: 44180 | AA91: INV2020/00000065 | AB91: 0 | AH91: 0 | AT91: 7 | AV91: 0 | BA91: 0
X92: 2021 | Y92: 1 | Z92: 44225 | AA92: INV2020/00000075 | AB92: 0 | AH92: 0 | AT92: 10 | AV92: 0 | BA92: 0
Y93: 2 | Z93: 44246 | AA93: INV2020/00000082 | AB93: 0 | AH93: 0 | AT93: 11 | AV93: 0 | BA93: 0
Y94: 5 | Z94: 44323 | AA94: INV00000104 | AB94: 0 | AH94: 0 | AT94: 12 | AV94: 0 | BA94: 0
Y95: 9 | Z95: 44464 | AA95: INV00000120 | AB95: 0 | AH95: 0 | AS95: 2022 | AT95: 1 | AV95: 0 | BA95: 0
Y96: 10 | Z96: 44495 | AA96: INV00000143 | AB96: 0 | AH96: 0 | AT96: 2 | AV96: 0 | BA96: 0
Y97: 12 | Z97: 44558 | AA97: INV00000178 | AB97: 0 | AH97: 0 | AT97: 5 | AV97: 0 | BA97: 0
Y98: 4 | Z98: 44295 | AA98: INV00000099 | AB98: 0 | AH98: 0 | AT98: 6 | AV98: 0 | BA98: 0
X99: 2019 | Y99: 12 | Z99: 43822 | AA99: INV2019/00000001 | AB99: 0 | AH99: 0 | AT99: 9 | AV99: 0 | BA99: 0
X100: 2022 | Y100: 3 | Z100: 44649 | AA100: INV00000225 | AB100: 0 | AH100: 0 | AT100: 11 | AV100: 0 | BA100: 0
Y101: 6 | Z101: 44719 | AA101: INV00000281 | AB101: 0 | AH101: 0 | AT101: 4 | AV101: 0 | BA101: 0
...

Sheet Raw Sales
A1: Invoice Date | B1: Period (Sales) | C1: Year (Sales) | D1: Invoice No | E1: Customer Code | F1: Customer Name | G1: Product | H1: Qty | I1: Payment Term | J1: Term | K1: Due date | L1: Period (Due) | M1: Year (Due) | N1: Sales Amount | O1: Collection | P1: Outstanding | Q1: Total Sales | R1: Payment mode | S1: Remark | T1: Remark2
A2: 43822 | B2: =MONTH(A2) -> 12 | C2: =YEAR(A2) -> 2019 | D2: INV2019/00000001 | E2: =VLOOKUP(F2,'Set up'!$A$2:$C$70,2,FALSE) -> C00000001 | F2: Kelnico Marketing | G2: RA Resin SHCP 268W (225kg) | H2: 1 | I2: =VLOOKUP(F2,'Set up'!$A$2:$C$70,3,FALSE) -> Cash | J2: =VLOOKUP(F2,'Set up'!$A$2:$D$70,4,FALSE) -> 0 | K2: =A2+J2 -> 43822 | L2: =MONTH(K2) -> 12 | M2: =YEAR(K2) -> 2019 | N2: 1530 | O2: =SUM(-N2) -> -1530 | P2: =SUM(N2+O2) -> 0 | Q2: =N2 -> 1530 | R2: =VLOOKUP(F2,'Set up'!$A$2:$E$70,5,FALSE) -> Trsf | S2: Trsf 29/5
A3: 43822 | B3: =MONTH(A3) -> 12 | C3: =YEAR(A3) -> 2019 | D3: INV2019/00000001 | E3: =VLOOKUP(F3,'Set up'!$A$2:$C$70,2,FALSE) -> C00000001 | F3: Kelnico Marketing | G3: RA CSM 450 GSM JUSHI 37kg 79m(L) X 1040mm(W) | H3: 6 | I3: =VLOOKUP(F3,'Set up'!$A$2:$C$70,3,FALSE) -> Cash | J3: =VLOOKUP(F3,'Set up'!$A$2:$D$70,4,FALSE) -> 0 | K3: =A3+J3 -> 43822 | L3: =MONTH(K3) -> 12 | M3: =YEAR(K3) -> 2019 | N3: 1443 | O3: =SUM(-N3) -> -1443 | P3: =SUM(N3+O3) -> 0 | Q3: =SUM(Q2+N3) -> 2973 | R3: =VLOOKUP(F3,'Set up'!$A$2:$E$70,5,FALSE) -> Trsf | S3: Trsf 29/5
A4: 43984 | B4: =MONTH(A4) -> 6 | C4: =YEAR(A4) -> 2020 | D4: INV2020/00000002 | E4: =VLOOKUP(F4,'Set up'!$A$2:$C$70,2,FALSE) -> C00000001 | F4: Kelnico Marketing | G4: RA Gelcoat GS-S ISO (20kg) | H4: 2 | I4: =VLOOKUP(F4,'Set up'!$A$2:$C$70,3,FALSE) -> Cash | J4: =VLOOKUP(F4,'Set up'!$A$2:$D$70,4,FALSE) -> 0 | K4: =A4+J4 -> 43984 | L4: =MONTH(K4) -> 6 | M4: =YEAR(K4) -> 2020 | N4: 480 | O4: =SUM(-N4) -> -480 | P4: =SUM(N4+O4) -> 0 | Q4: =SUM(Q3+N4) -> 3453 | R4: =VLOOKUP(F4,'Set up'!$A$2:$E$70,5,FALSE) -> Trsf | S4: Trsf 24/6
A5: 43993 | B5: =MONTH(A5) -> 6 | C5: =YEAR(A5) -> 2020 | D5: INV2020/00000003 | E5: =VLOOKUP(F5,'Set up'!$A$2:$C$70,2,FALSE) -> C00000002 | F5: Sley | G5: RA Resin SHCP 268W (225Kg) | H5: 1 | I5: =VLOOKUP(F5,'Set up'!$A$2:$C$70,3,FALSE) -> Cash | J5: =VLOOKUP(F5,'Set up'!$A$2:$D$70,4,FALSE) -> 0 | K5: =A5+J5 -> 43993 | L5: =MONTH(K5) -> 6 | M5: =YEAR(K5) -> 2020 | N5: 1395 | O5: =SUM(-N5) -> -1395 | P5: =SUM(N5+O5) -> 0 | Q5: =SUM(Q4+N5) -> 4848 | R5: =VLOOKUP(F5,'Set up'!$A$2:$E$70,5,FALSE) -> Chq | S5: Chq 13/6
A6: 43993 | B6: =MONTH(A6) -> 6 | C6: =YEAR(A6) -> 2020 | D6: INV2020/00000003 | E6: =VLOOKUP(F6,'Set up'!$A$2:$C$70,2,FALSE) -> C00000002 | F6: Sley | G6: RB Acetone (160Kg) | H6: 1 | I6: =VLOOKUP(F6,'Set up'!$A$2:$C$70,3,FALSE) -> Cash | J6: =VLOOKUP(F6,'Set up'!$A$2:$D$70,4,FALSE) -> 0 | K6: =A6+J6 -> 43993 | L6: =MONTH(K6) -> 6 | M6: =YEAR(K6) -> 2020 | N6: 672 | O6: =SUM(-N6) -> -672 | P6: =SUM(N6+O6) -> 0 | Q6: =SUM(Q5+N6) -> 5520 | R6: =VLOOKUP(F6,'Set up'!$A$2:$E$70,5,FALSE) -> Chq | S6: Chq 13/6
A7: 43999 | B7: =MONTH(A7) -> 6 | C7: =YEAR(A7) -> 2020 | D7: INV2020/00000004 | E7: =VLOOKUP(F7,'Set up'!$A$2:$C$70,2,FALSE) -> C00000001 | F7: Kelnico Marketing | G7: RA Resin SHCP 268W (225kg) | H7: 1 | I7: =VLOOKUP(F7,'Set up'!$A$2:$C$70,3,FALSE) -> Cash | J7: =VLOOKUP(F7,'Set up'!$A$2:$D$70,4,FALSE) -> 0 | K7: =A7+J7 -> 43999 | L7: =MONTH(K7) -> 6 | M7: =YEAR(K7) -> 2020 | N7: 1530 | O7: =SUM(-N7) -> -1530 | P7: =SUM(N7+O7) -> 0 | Q7: =SUM(Q6+N7) -> 7050 | R7: =VLOOKUP(F7,'Set up'!$A$2:$E$70,5,FALSE) -> Trsf | S7: Trsf 24/6
A8: 43999 | B8: =MONTH(A8) -> 6 | C8: =YEAR(A8) -> 2020 | D8: INV2020/00000004 | E8: =VLOOKUP(F8,'Set up'!$A$2:$C$70,2,FALSE) -> C00000001 | F8: Kelnico Marketing | G8: RA CSM 450 GSM JUSHI 37kg 79m(L) X 1040mm(W) | H8: 3 | I8: =VLOOKUP(F8,'Set up'!$A$2:$C$70,3,FALSE) -> Cash | J8: =VLOOKUP(F8,'Set up'!$A$2:$D$70,4,FALSE) -> 0 | K8: =A8+J8 -> 43999 | L8: =MONTH(K8) -> 6 | M8: =YEAR(K8) -> 2020 | N8: 720 | O8: =SUM(-N8) -> -720 | P8: =SUM(N8+O8) -> 0 | Q8: =SUM(Q7+N8) -> 7770 | R8: =VLOOKUP(F8,'Set up'!$A$2:$E$70,5,FALSE) -> Trsf | S8: Trsf 24/6
A9: 43999 | B9: =MONTH(A9) -> 6 | C9: =YEAR(A9) -> 2020 | D9: INV2020/00000004 | E9: =VLOOKUP(F9,'Set up'!$A$2:$C$70,2,FALSE) -> C00000001 | F9: Kelnico Marketing | G9: RA Butanox M50 (5Kg) | H9: 2 | I9: =VLOOKUP(F9,'Set up'!$A$2:$C$70,3,FALSE) -> Cash | J9: =VLOOKUP(F9,'Set up'!$A$2:$D$70,4,FALSE) -> 0 | K9: =A9+J9 -> 43999 | L9: =MONTH(K9) -> 6 | M9: =YEAR(K9) -> 2020 | N9: 185 | O9: =SUM(-N9) -> -185 | P9: =SUM(N9+O9) -> 0 | Q9: =SUM(Q8+N9) -> 7955 | R9: =VLOOKUP(F9,'Set up'!$A$2:$E$70,5,FALSE) -> Trsf | S9: Trsf 24/6
A10: 44004 | B10: =MONTH(A10) -> 6 | C10: =YEAR(A10) -> 2020 | D10: INV2020/00000005 | E10: =VLOOKUP(F10,'Set up'!$A$2:$C$70,2,FALSE) -> C00000003 | F10: Pandian Art Gallery Manufacturing | G10: RA Resin SHCP 268W (225kg) | H10: 1 | I10: =VLOOKUP(F10,'Set up'!$A$2:$C$70,3,FALSE) -> 45 | J10: =VLOOKUP(F10,'Set up'!$A$2:$D$70,4,FALSE) -> 45 | K10: =A10+J10 -> 44049 | L10: =MONTH(K10) -> 8 | M10: =YEAR(K10) -> 2020 | N10: 1642.5 | O10: =SUM(-N10) -> -1642.5 | P10: =SUM(N10+O10) -> 0 | Q10: =SUM(Q9+N10) -> 9597.5 | R10: =VLOOKUP(F10,'Set up'!$A$2:$E$70,5,FALSE) -> PD Chq | S10: PD chq 8/8, RM1,827.00 & Cash RM0.50
A11: 44004 | B11: =MONTH(A11) -> 6 | C11: =YEAR(A11) -> 2020 | D11: INV2020/00000005 | E11: =VLOOKUP(F11,'Set up'!$A$2:$C$70,2,FALSE) -> C00000003 | F11: Pandian Art Gallery Manufacturing | G11: RA Butanox M50 (5Kg) | H11: 2 | I11: =VLOOKUP(F11,'Set up'!$A$2:$C$70,3,FALSE) -> 45 | J11: =VLOOKUP(F11,'Set up'!$A$2:$D$70,4,FALSE) -> 45 | K11: =A11+J11 -> 44049 | L11: =MONTH(K11) -> 8 | M11: =YEAR(K11) -> 2020 | N11: 185 | O11: =SUM(-N11) -> -185 | P11: =SUM(N11+O11) -> 0 | Q11: =SUM(Q10+N11) -> 9782.5 | R11: =VLOOKUP(F11,'Set up'!$A$2:$E$70,5,FALSE) -> PD Chq | S11: PD chq 8/8, RM1,827.00 & Cash RM0.50
A12: 44013 | B12: =MONTH(A12) -> 7 | C12: =YEAR(A12) -> 2020 | D12: INV2020/00000006 | E12: =VLOOKUP(F12,'Set up'!$A$2:$C$70,2,FALSE) -> C00000004 | F12: Siew Min Lorry Sdn Bhd | G12: RA Gelcoat GP-H (20Kg) | H12: 9 | I12: =VLOOKUP(F12,'Set up'!$A$2:$C$70,3,FALSE) -> 120 | J12: =VLOOKUP(F12,'Set up'!$A$2:$D$70,4,FALSE) -> 120 | K12: =A12+J12 -> 44133 | L12: =MONTH(K12) -> 10 | M12: =YEAR(K12) -> 2020 | N12: 1836 | O12: =SUM(-N12) -> -1836 | P12: =SUM(N12+O12) -> 0 | Q12: =SUM(Q11+N12) -> 11618.5 | R12: =VLOOKUP(F12,'Set up'!$A$2:$E$70,5,FALSE) -> Chq | S12: Chq 16/11/2020
A13: 44026 | B13: =MONTH(A13) -> 7 | C13: =YEAR(A13) -> 2020 | D13: INV2020/00000007 | E13: =VLOOKUP(F13,'Set up'!$A$2:$C$70,2,FALSE) -> C00000003 | F13: Pandian Art Gallery Manufacturing | G13: RA Silicone Rubber (25Kg) | H13: 1 | I13: =VLOOKUP(F13,'Set up'!$A$2:$C$70,3,FALSE) -> 45 | J13: =VLOOKUP(F13,'Set up'!$A$2:$D$70,4,FALSE) -> 45 | K13: =A13+J13 -> 44071 | L13: =MONTH(K13) -> 8 | M13: =YEAR(K13) -> 2020 | N13: 1200 | O13: =SUM(-N13) -> -1200 | P13: =SUM(N13+O13) -> 0 | Q13: =SUM(Q12+N13) -> 12818.5 | R13: =VLOOKUP(F13,'Set up'!$A$2:$E$70,5,FALSE) -> PD Chq | S13: PD chq 16/8
A14: 44027 | B14: =MONTH(A14) -> 7 | C14: =YEAR(A14) -> 2020 | D14: INV2020/00000008 | E14: =VLOOKUP(F14,'Set up'!$A$2:$C$70,2,FALSE) -> C00000001 | F14: Kelnico Marketing | G14: RA Nor 3338W (220Kg) | H14: 1 | I14: =VLOOKUP(F14,'Set up'!$A$2:$C$70,3,FALSE) -> Cash | J14: =VLOOKUP(F14,'Set up'!$A$2:$D$70,4,FALSE) -> 0 | K14: =A14+J14 -> 44027 | L14: =MONTH(K14) -> 7 | M14: =YEAR(K14) -> 2020 | N14: 1496 | O14: =SUM(-N14) -> -1496 | P14: =SUM(N14+O14) -> 0 | Q14: =SUM(Q13+N14) -> 14314.5 | R14: =VLOOKUP(F14,'Set up'!$A$2:$E$70,5,FALSE) -> Trsf | S14: Trsf 28/7
A15: 44027 | B15: =MONTH(A15) -> 7 | C15: =YEAR(A15) -> 2020 | D15: INV2020/00000008 | E15: =VLOOKUP(F15,'Set up'!$A$2:$C$70,2,FALSE) -> C00000001 | F15: Kelnico Marketing | G15: RA Butanox M50 (5Kg) | H15: 4 | I15: =VLOOKUP(F15,'Set up'!$A$2:$C$70,3,FALSE) -> Cash | J15: =VLOOKUP(F15,'Set up'!$A$2:$D$70,4,FALSE) -> 0 | K15: =A15+J15 -> 44027 | L15: =MONTH(K15) -> 7 | M15: =YEAR(K15) -> 2020 | N15: 370 | O15: =SUM(-N15) -> -370 | P15: =SUM(N15+O15) -> 0 | Q15: =SUM(Q14+N15) -> 14684.5 | R15: =VLOOKUP(F15,'Set up'!$A$2:$E$70,5,FALSE) -> Trsf | S15: Trsf 28/7
A16: 44027 | B16: =MONTH(A16) -> 7 | C16: =YEAR(A16) -> 2020 | D16: INV2020/00000008 | E16: =VLOOKUP(F16,'Set up'!$A$2:$C$70,2,FALSE) -> C00000001 | F16: Kelnico Marketing | G16: RC Woven Roving E-800 40Kg 1000mm | H16: 1 | I16: =VLOOKUP(F16,'Set up'!$A$2:$C$70,3,FALSE) -> Cash | J16: =VLOOKUP(F16,'Set up'!$A$2:$D$70,4,FALSE) -> 0 | K16: =A16+J16 -> 44027 | L16: =MONTH(K16) -> 7 | M16: =YEAR(K16) -> 2020 | N16: 232 | O16: =SUM(-N16) -> -232 | P16: =SUM(N16+O16) -> 0 | Q16: =SUM(Q15+N16) -> 14916.5 | R16: =VLOOKUP(F16,'Set up'!$A$2:$E$70,5,FALSE) -> Trsf | S16: Trsf 28/7 | T16: Delivered 22/7/20
A17: 44044 | B17: =MONTH(A17) -> 8 | C17: =YEAR(A17) -> 2020 | D17: INV2020/00000009 | E17: =VLOOKUP(F17,'Set up'!$A$2:$C$70,2,FALSE) -> C00000004 | F17: Siew Min Lorry Sdn Bhd | G17: RA Nor 3338W (220Kg) | H17: 2 | I17: =VLOOKUP(F17,'Set up'!$A$2:$C$70,3,FALSE) -> 120 | J17: =VLOOKUP(F17,'Set up'!$A$2:$D$70,4,FALSE) -> 120 | K17: =A17+J17 -> 44164 | L17: =MONTH(K17) -> 11 | M17: =YEAR(K17) -> 2020 | N17: 2508 | O17: =SUM(-N17) -> -2508 | P17: =SUM(N17+O17) -> 0 | Q17: =SUM(Q16+N17) -> 17424.5 | R17: =VLOOKUP(F17,'Set up'!$A$2:$E$70,5,FALSE) -> Chq | S17: Chq 1/12/2020
A18: 44051 | B18: =MONTH(A18) -> 8 | C18: =YEAR(A18) -> 2020 | D18: INV2020/00000010 | E18: =VLOOKUP(F18,'Set up'!$A$2:$C$70,2,FALSE) -> C00000004 | F18: Siew Min Lorry Sdn Bhd | G18: RA Nor 3338W (220Kg) | H18: 2 | I18: =VLOOKUP(F18,'Set up'!$A$2:$C$70,3,FALSE) -> 120 | J18: =VLOOKUP(F18,'Set up'!$A$2:$D$70,4,FALSE) -> 120 | K18: =A18+J18 -> 44171 | L18: =MONTH(K18) -> 12 | M18: =YEAR(K18) -> 2020 | N18: 2508 | O18: =SUM(-N18) -> -2508 | P18: =SUM(N18+O18) -> 0 | Q18: =SUM(Q17+N18) -> 19932.5 | R18: =VLOOKUP(F18,'Set up'!$A$2:$E$70,5,FALSE) -> Chq | S18: Chq 1/12/2020
A19: 44051 | B19: =MONTH(A19) -> 8 | C19: =YEAR(A19) -> 2020 | D19: INV2020/00000011 | E19: =VLOOKUP(F19,'Set up'!$A$2:$C$70,2,FALSE) -> C00000004 | F19: Siew Min Lorry Sdn Bhd | G19: RA CSM 300 GSM TWL 30kg 64m(L) x 1040mm(W) | H19: 2 | I19: =VLOOKUP(F19,'Set up'!$A$2:$C$70,3,FALSE) -> 120 | J19: =VLOOKUP(F19,'Set up'!$A$2:$D$70,4,FALSE) -> 120 | K19: =A19+J19 -> 44171 | L19: =MONTH(K19) -> 12 | M19: =YEAR(K19) -> 2020 | N19: 324 | O19: =SUM(-N19) -> -324 | P19: =SUM(N19+O19) -> 0 | Q19: =SUM(Q18+N19) -> 20256.5 | R19: =VLOOKUP(F19,'Set up'!$A$2:$E$70,5,FALSE) -> Chq | S19: Chq 1/12/2020
A20: 44053 | B20: =MONTH(A20) -> 8 | C20: =YEAR(A20) -> 2020 | D20: INV2020/00000012 | E20: =VLOOKUP(F20,'Set up'!$A$2:$C$70,2,FALSE) -> C00000005 | F20: Artscene Creative | G20: RA Nor 3338W (220Kg) | H20: 1 | I20: =VLOOKUP(F20,'Set up'!$A$2:$C$70,3,FALSE) -> Cash | J20: =VLOOKUP(F20,'Set up'!$A$2:$D$70,4,FALSE) -> 0 | K20: =A20+J20 -> 44053 | L20: =MONTH(K20) -> 8 | M20: =YEAR(K20) -> 2020 | N20: 1496 | O20: =SUM(-N20) -> -1496 | P20: =SUM(N20+O20) -> 0 | Q20: =SUM(Q19+N20) -> 21752.5 | R20: =VLOOKUP(F20,'Set up'!$A$2:$E$70,5,FALSE) -> Chq | S20: Chq 10/8
A21: 44053 | B21: =MONTH(A21) -> 8 | C21: =YEAR(A21) -> 2020 | D21: INV2020/00000012 | E21: =VLOOKUP(F21,'Set up'!$A$2:$C$70,2,FALSE) -> C00000005 | F21: Artscene Creative | G21: RA Butanox M50 (5Kg) | H21: 1 | I21: =VLOOKUP(F21,'Set up'!$A$2:$C$70,3,FALSE) -> Cash | J21: =VLOOKUP(F21,'Set up'!$A$2:$D$70,4,FALSE) -> 0 | K21: =A21+J21 -> 44053 | L21: =MONTH(K21) -> 8 | M21: =YEAR(K21) -> 2020 | N21: 90 | O21: =SUM(-N21) -> -90 | P21: =SUM(N21+O21) -> 0 | Q21: =SUM(Q20+N21) -> 21842.5 | R21: =VLOOKUP(F21,'Set up'!$A$2:$E$70,5,FALSE) -> Chq | S21: Chq 10/8
A22: 44053 | B22: =MONTH(A22) -> 8 | C22: =YEAR(A22) -> 2020 | D22: INV2020/00000013 | E22: =VLOOKUP(F22,'Set up'!$A$2:$C$70,2,FALSE) -> C00000003 | F22: Pandian Art Gallery Manufacturing | G22: RA Nor 3338W (220Kg) | H22: 2 | I22: =VLOOKUP(F22,'Set up'!$A$2:$C$70,3,FALSE) -> 45 | J22: =VLOOKUP(F22,'Set up'!$A$2:$D$70,4,FALSE) -> 45 | K22: =A22+J22 -> 44098 | L22: =MONTH(K22) -> 9 | M22: =YEAR(K22) -> 2020 | N22: 3036 | O22: =SUM(-N22) -> -3036 | P22: =SUM(N22+O22) -> 0 | Q22: =SUM(Q21+N22) -> 24878.5 | R22: =VLOOKUP(F22,'Set up'!$A$2:$E$70,5,FALSE) -> PD Chq | S22: PD chq 13/9, RM1,700/- & 20/9, RM1,706/-
A23: 44053 | B23: =MONTH(A23) -> 8 | C23: =YEAR(A23) -> 2020 | D23: INV2020/00000013 | E23: =VLOOKUP(F23,'Set up'!$A$2:$C$70,2,FALSE) -> C00000003 | F23: Pandian Art Gallery Manufacturing | G23: RA Butanox M50 (5Kg) | H23: 4 | I23: =VLOOKUP(F23,'Set up'!$A$2:$C$70,3,FALSE) -> 45 | J23: =VLOOKUP(F23,'Set up'!$A$2:$D$70,4,FALSE) -> 45 | K23: =A23+J23 -> 44098 | L23: =MONTH(K23) -> 9 | M23: =YEAR(K23) -> 2020 | N23: 370 | O23: =SUM(-N23) -> -370 | P23: =SUM(N23+O23) -> 0 | Q23: =SUM(Q22+N23) -> 25248.5 | R23: =VLOOKUP(F23,'Set up'!$A$2:$E$70,5,FALSE) -> PD Chq | S23: PD chq 13/9, RM1,700/- & 20/9, RM1,706/-
A24: 44055 | B24: =MONTH(A24) -> 8 | C24: =YEAR(A24) -> 2020 | D24: INV2020/00000014 | E24: =VLOOKUP(F24,'Set up'!$A$2:$C$70,2,FALSE) -> C00000001 | F24: Kelnico Marketing | G24: RA Nor 3338W (220Kg) | H24: 1 | I24: =VLOOKUP(F24,'Set up'!$A$2:$C$70,3,FALSE) -> Cash | J24: =VLOOKUP(F24,'Set up'!$A$2:$D$70,4,FALSE) -> 0 | K24: =A24+J24 -> 44055 | L24: =MONTH(K24) -> 8 | M24: =YEAR(K24) -> 2020 | N24: 1496 | O24: =SUM(-N24) -> -1496 | P24: =SUM(N24+O24) -> 0 | Q24: =SUM(Q23+N24) -> 26744.5 | R24: =VLOOKUP(F24,'Set up'!$A$2:$E$70,5,FALSE) -> Trsf | S24: Trsf 23/8
A25: 44055 | B25: =MONTH(A25) -> 8 | C25: =YEAR(A25) -> 2020 | D25: INV2020/00000014 | E25: =VLOOKUP(F25,'Set up'!$A$2:$C$70,2,FALSE) -> C00000001 | F25: Kelnico Marketing | G25: RA CSM 450 GSM JUSHI 37kg 79m(L) X 1040mm(W) | H25: 4 | I25: =VLOOKUP(F25,'Set up'!$A$2:$C$70,3,FALSE) -> Cash | J25: =VLOOKUP(F25,'Set up'!$A$2:$D$70,4,FALSE) -> 0 | K25: =A25+J25 -> 44055 | L25: =MONTH(K25) -> 8 | M25: =YEAR(K25) -> 2020 | N25: 962 | O25: =SUM(-N25) -> -962 | P25: =SUM(N25+O25) -> 0 | Q25: =SUM(Q24+N25) -> 27706.5 | R25: =VLOOKUP(F25,'Set up'!$A$2:$E$70,5,FALSE) -> Trsf | S25: Trsf 23/8
A26: 44055 | B26: =MONTH(A26) -> 8 | C26: =YEAR(A26) -> 2020 | D26: INV2020/00000014 | E26: =VLOOKUP(F26,'Set up'!$A$2:$C$70,2,FALSE) -> C00000001 | F26: Kelnico Marketing | G26: RC Woven Roving E-800 40Kg 1000mm | H26: 2 | I26: =VLOOKUP(F26,'Set up'!$A$2:$C$70,3,FALSE) -> Cash | J26: =VLOOKUP(F26,'Set up'!$A$2:$D$70,4,FALSE) -> 0 | K26: =A26+J26 -> 44055 | L26: =MONTH(K26) -> 8 | M26: =YEAR(K26) -> 2020 | N26: 464 | O26: =SUM(-N26) -> -464 | P26: =SUM(N26+O26) -> 0 | Q26: =SUM(Q25+N26) -> 28170.5 | R26: =VLOOKUP(F26,'Set up'!$A$2:$E$70,5,FALSE) -> Trsf | S26: Trsf 23/8
A27: 44056 | B27: =MONTH(A27) -> 8 | C27: =YEAR(A27) -> 2020 | D27: INV2020/00000015 | E27: =VLOOKUP(F27,'Set up'!$A$2:$C$70,2,FALSE) -> C00000001 | F27: Kelnico Marketing | G27: RA Gelcoat GS-S ISO (20kg) | H27: 4 | I27: =VLOOKUP(F27,'Set up'!$A$2:$C$70,3,FALSE) -> Cash | J27: =VLOOKUP(F27,'Set up'!$A$2:$D$70,4,FALSE) -> 0 | K27: =A27+J27 -> 44056 | L27: =MONTH(K27) -> 8 | M27: =YEAR(K27) -> 2020 | N27: 960 | O27: =SUM(-N27) -> -960 | P27: =SUM(N27+O27) -> 0 | Q27: =SUM(Q26+N27) -> 29130.5 | R27: =VLOOKUP(F27,'Set up'!$A$2:$E$70,5,FALSE) -> Trsf | S27: Trsf 23/8
A28: 44062 | B28: =MONTH(A28) -> 8 | C28: =YEAR(A28) -> 2020 | D28: INV2020/00000016 | E28: =VLOOKUP(F28,'Set up'!$A$2:$C$70,2,FALSE) -> C00000003 | F28: Pandian Art Gallery Manufacturing | G28: RA CSM 450 GSM 54kg 64m(L) X 1860mm(W) | H28: 1 | I28: =VLOOKUP(F28,'Set up'!$A$2:$C$70,3,FALSE) -> 45 | J28: =VLOOKUP(F28,'Set up'!$A$2:$D$70,4,FALSE) -> 45 | K28: =A28+J28 -> 44107 | L28: =MONTH(K28) -> 10 | M28: =YEAR(K28) -> 2020 | N28: 367.2 | O28: =SUM(-N28) -> -367.2 | P28: =SUM(N28+O28) -> 0 | Q28: =SUM(Q27+N28) -> 29497.7 | R28: =VLOOKUP(F28,'Set up'!$A$2:$E$70,5,FALSE) -> PD Chq | S28: PD Chq 27/9, RM1,270.20
... A41: 44068 | B41: =MONTH(A41) -> 8 | C41: =YEAR(A41) -> 2020 | D41: INV2020/00000022 | E41: =VLOOKUP(F41,'Set up'!$A$2:$C$70,2,FALSE) -> C00000001 | F41: Kelnico Marketing | G41: RA Nor 3338W (220Kg) | H41: 1 | I41: =VLOOKUP(F41,'Set up'!$A$2:$C$70,3,FALSE) -> Cash | J41: =VLOOKUP(F41,'Set up'!$A$2:$D$70,4,FALSE) -> 0 | K41: =A41+J41 -> 44068 | L41: =MONTH(K41) -> 8 | M41: =YEAR(K41) -> 2020 | N41: 1496 | O41: =SUM(-N41) -> -1496 | P41: =SUM(N41+O41) -> 0 | Q41: =SUM(Q40+N41) -> 41562.7 | R41: =VLOOKUP(F41,'Set up'!$A$2:$E$70,5,FALSE) -> Trsf | S41: Trsf 1/9/2020
A42: 44070 | B42: =MONTH(A42) -> 8 | C42: =YEAR(A42) -> 2020 | D42: INV2020/00000023 | E42: =VLOOKUP(F42,'Set up'!$A$2:$C$70,2,FALSE) -> C00000010 | F42: Yew Seng Gardening Supply Sdn Bhd | G42: RA Nor 3338W (220Kg) | H42: 4 | I42: =VLOOKUP(F42,'Set up'!$A$2:$C$70,3,FALSE) -> 120 | J42: =VLOOKUP(F42,'Set up'!$A$2:$D$70,4,FALSE) -> 120 | K42: =A42+J42 -> 44190 | L42: =MONTH(K42) -> 12 | M42: =YEAR(K42) -> 2020 | N42: 5280 | O42: -5280 | P42: =SUM(N42+O42) -> 0 | Q42: =SUM(Q41+N42) -> 46842.7 | R42: =VLOOKUP(F42,'Set up'!$A$2:$E$70,5,FALSE) -> Trsf | S42: Trsf 23/12/2020
A43: 44070 | B43: =MONTH(A43) -> 8 | C43: =YEAR(A43) -> 2020 | D43: INV2020/00000023 | E43: =VLOOKUP(F43,'Set up'!$A$2:$C$70,2,FALSE) -> C00000010 | F43: Yew Seng Gardening Supply Sdn Bhd | G43: RA CSM 450 GSM JUSHI 37kg 79m(L) X 1040mm(W) | H43: 2 | I43: =VLOOKUP(F43,'Set up'!$A$2:$C$70,3,FALSE) -> 120 | J43: =VLOOKUP(F43,'Set up'!$A$2:$D$70,4,FALSE) -> 120 | K43: =A43+J43 -> 44190 | L43: =MONTH(K43) -> 12 | M43: =YEAR(K43) -> 2020 | N43: 444 | O43: -444 | P43: =SUM(N43+O43) -> 0 | Q43: =SUM(Q42+N43) -> 47286.7 | R43: =VLOOKUP(F43,'Set up'!$A$2:$E$70,5,FALSE) -> Trsf | S43: Trsf 23/12/2020
A44: 44070 | B44: =MONTH(A44) -> 8 | C44: =YEAR(A44) -> 2020 | D44: INV2020/00000023 | E44: =VLOOKUP(F44,'Set up'!$A$2:$C$70,2,FALSE) -> C00000010 | F44: Yew Seng Gardening Supply Sdn Bhd | G44: RA Talcum Powder (25kg) | H44: 5 | I44: =VLOOKUP(F44,'Set up'!$A$2:$C$70,3,FALSE) -> 120 | J44: =VLOOKUP(F44,'Set up'!$A$2:$D$70,4,FALSE) -> 120 | K44: =A44+J44 -> 44190 | L44: =MONTH(K44) -> 12 | M44: =YEAR(K44) -> 2020 | N44: 275 | O44: -275 | P44: =SUM(N44+O44) -> 0 | Q44: =SUM(Q43+N44) -> 47561.7 | R44: =VLOOKUP(F44,'Set up'!$A$2:$E$70,5,FALSE) -> Trsf | S44: Trsf 23/12/2020
A45: 44070 | B45: =MONTH(A45) -> 8 | C45: =YEAR(A45) -> 2020 | D45: INV2020/00000023 | E45: =VLOOKUP(F45,'Set up'!$A$2:$C$70,2,FALSE) -> C00000010 | F45: Yew Seng Gardening Supply Sdn Bhd | G45: RA Butanox M50 (5kg) | H45: 4 | I45: =VLOOKUP(F45,'Set up'!$A$2:$C$70,3,FALSE) -> 120 | J45: =VLOOKUP(F45,'Set up'!$A$2:$D$70,4,FALSE) -> 120 | K45: =A45+J45 -> 44190 | L45: =MONTH(K45) -> 12 | M45: =YEAR(K45) -> 2020 | N45: 360 | O45: -360 | P45: =SUM(N45+O45) -> 0 | Q45: =SUM(Q44+N45) -> 47921.7 | R45: =VLOOKUP(F45,'Set up'!$A$2:$E$70,5,FALSE) -> Trsf | S45: Trsf 23/12/2020
A46: 44070 | B46: =MONTH(A46) -> 8 | C46: =YEAR(A46) -> 2020 | D46: INV2020/00000023 | E46: =VLOOKUP(F46,'Set up'!$A$2:$C$70,2,FALSE) -> C00000010 | F46: Yew Seng Gardening Supply Sdn Bhd | G46: RA Bosny Wax (15kg) | H46: 1 | I46: =VLOOKUP(F46,'Set up'!$A$2:$C$70,3,FALSE) -> 120 | J46: =VLOOKUP(F46,'Set up'!$A$2:$D$70,4,FALSE) -> 120 | K46: =A46+J46 -> 44190 | L46: =MONTH(K46) -> 12 | M46: =YEAR(K46) -> 2020 | N46: 375 | O46: -375 | P46: =SUM(N46+O46) -> 0 | Q46: =SUM(Q45+N46) -> 48296.7 | R46: =VLOOKUP(F46,'Set up'!$A$2:$E$70,5,FALSE) -> Trsf | S46: Trsf 23/12/2020
A47: 44075 | B47: =MONTH(A47) -> 9 | C47: =YEAR(A47) -> 2020 | D47: INV2020/00000024 | E47: =VLOOKUP(F47,'Set up'!$A$2:$C$70,2,FALSE) -> C00000008 | F47: Wonderland Design Productions Studio | G47: RA Resin 3317AW (220Kg) | H47: 2 | I47: =VLOOKUP(F47,'Set up'!$A$2:$C$70,3,FALSE) -> Cash | J47: =VLOOKUP(F47,'Set up'!$A$2:$D$70,4,FALSE) -> 0 | K47: =A47+J47 -> 44075 | L47: =MONTH(K47) -> 9 | M47: =YEAR(K47) -> 2020 | N47: 2948 | O47: =SUM(-N47) -> -2948 | P47: =SUM(N47+O47) -> 0 | Q47: =SUM(Q46+N47) -> 51244.7 | R47: =VLOOKUP(F47,'Set up'!$A$2:$E$70,5,FALSE) -> Trsf | S47: Trsf 7/9/2020
A48: 44075 | B48: =MONTH(A48) -> 9 | C48: =YEAR(A48) -> 2020 | D48: INV2020/00000024 | E48: =VLOOKUP(F48,'Set up'!$A$2:$C$70,2,FALSE) -> C00000008 | F48: Wonderland Design Productions Studio | G48: RA Gelcoat GP-H (20kg) | H48: 4 | I48: =VLOOKUP(F48,'Set up'!$A$2:$C$70,3,FALSE) -> Cash | J48: =VLOOKUP(F48,'Set up'!$A$2:$D$70,4,FALSE) -> 0 | K48: =A48+J48 -> 44075 | L48: =MONTH(K48) -> 9 | M48: =YEAR(K48) -> 2020 | N48: 840 | O48: =SUM(-N48) -> -840 | P48: =SUM(N48+O48) -> 0 | Q48: =SUM(Q47+N48) -> 52084.7 | R48: =VLOOKUP(F48,'Set up'!$A$2:$E$70,5,FALSE) -> Trsf | S48: Trsf 7/9/2020
A49: 44075 | B49: =MONTH(A49) -> 9 | C49: =YEAR(A49) -> 2020 | D49: INV2020/00000024 | E49: =VLOOKUP(F49,'Set up'!$A$2:$C$70,2,FALSE) -> C00000008 | F49: Wonderland Design Productions Studio | G49: RA Butanox M50 (5kg) | H49: 2 | I49: =VLOOKUP(F49,'Set up'!$A$2:$C$70,3,FALSE) -> Cash | J49: =VLOOKUP(F49,'Set up'!$A$2:$D$70,4,FALSE) -> 0 | K49: =A49+J49 -> 44075 | L49: =MONTH(K49) -> 9 | M49: =YEAR(K49) -> 2020 | N49: 180 | O49: =SUM(-N49) -> -180 | P49: =SUM(N49+O49) -> 0 | Q49: =SUM(Q48+N49) -> 52264.7 | R49: =VLOOKUP(F49,'Set up'!$A$2:$E$70,5,FALSE) -> Trsf | S49: Trsf 7/9/2020
A50: 44076 | B50: =MONTH(A50) -> 9 | C50: =YEAR(A50) -> 2020 | D50: INV2020/00000025 | E50: =VLOOKUP(F50,'Set up'!$A$2:$C$70,2,FALSE) -> C00000001 | F50: Kelnico Marketing | G50: RA Silicone Rubber (25Kg) | H50: 1 | I50: =VLOOKUP(F50,'Set up'!$A$2:$C$70,3,FALSE) -> Cash | J50: =VLOOKUP(F50,'Set up'!$A$2:$D$70,4,FALSE) -> 0 | K50: =A50+J50 -> 44076 | L50: =MONTH(K50) -> 9 | M50: =YEAR(K50) -> 2020 | N50: 1250 | O50: =SUM(-N50) -> -1250 | P50: =SUM(N50+O50) -> 0 | Q50: =SUM(Q49+N50) -> 53514.7 | R50: =VLOOKUP(F50,'Set up'!$A$2:$E$70,5,FALSE) -> Trsf | S50: Trsf 5/9/2020 | T50: Delived on 3/9/2020
A51: 44079 | B51: =MONTH(A51) -> 9 | C51: =YEAR(A51) -> 2020 | D51: INV2020/00000026 | E51: =VLOOKUP(F51,'Set up'!$A$2:$C$70,2,FALSE) -> C00000001 | F51: Kelnico Marketing | G51: RA Resin 3317AW (220Kg) | H51: 1 | I51: =VLOOKUP(F51,'Set up'!$A$2:$C$70,3,FALSE) -> Cash | J51: =VLOOKUP(F51,'Set up'!$A$2:$D$70,4,FALSE) -> 0 | K51: =A51+J51 -> 44079 | L51: =MONTH(K51) -> 9 | M51: =YEAR(K51) -> 2020 | N51: 1496 | O51: =SUM(-N51) -> -1496 | P51: =SUM(N51+O51) -> 0 | Q51: =SUM(Q50+N51) -> 55010.7 | R51: =VLOOKUP(F51,'Set up'!$A$2:$E$70,5,FALSE) -> Trsf | S51: Trsf 5/9/2020
A52: 44079 | B52: =MONTH(A52) -> 9 | C52: =YEAR(A52) -> 2020 | D52: INV2020/00000026 | E52: =VLOOKUP(F52,'Set up'!$A$2:$C$70,2,FALSE) -> C00000001 | F52: Kelnico Marketing | G52: RA CSM 450 GSM JUSHI 37kg 79m(L) X 1040mm(W) | H52: 4 | I52: =VLOOKUP(F52,'Set up'!$A$2:$C$70,3,FALSE) -> Cash | J52: =VLOOKUP(F52,'Set up'!$A$2:$D$70,4,FALSE) -> 0 | K52: =A52+J52 -> 44079 | L52: =MONTH(K52) -> 9 | M52: =YEAR(K52) -> 2020 | N52: 962 | O52: =SUM(-N52) -> -962 | P52: =SUM(N52+O52) -> 0 | Q52: =SUM(Q51+N52) -> 55972.7 | R52: =VLOOKUP(F52,'Set up'!$A$2:$E$70,5,FALSE) -> Trsf | S52: Trsf 5/9/2020
A53: 44091 | B53: =MONTH(A53) -> 9 | C53: =YEAR(A53) -> 2020 | D53: INV2020/00000027 | E53: =VLOOKUP(F53,'Set up'!$A$2:$C$70,2,FALSE) -> C00000004 | F53: Siew Min Lorry Sdn Bhd | G53: RA Nor 3338W (220Kg) | H53: 5 | I53: =VLOOKUP(F53,'Set up'!$A$2:$C$70,3,FALSE) -> 120 | J53: =VLOOKUP(F53,'Set up'!$A$2:$D$70,4,FALSE) -> 120 | K53: =A53+J53 -> 44211 | L53: =MONTH(K53) -> 1 | M53: =YEAR(K53) -> 2021 | N53: 6270 | O53: =SUM(-N53) -> -6270 | P53: =SUM(N53+O53) -> 0 | Q53: =SUM(Q52+N53) -> 62242.7 | R53: =VLOOKUP(F53,'Set up'!$A$2:$E$70,5,FALSE) -> Chq | S53: PD HLB 004649, 25/1/2021
A54: 44091 | B54: =MONTH(A54) -> 9 | C54: =YEAR(A54) -> 2020 | D54: INV2020/00000027 | E54: =VLOOKUP(F54,'Set up'!$A$2:$C$70,2,FALSE) -> C00000004 | F54: Siew Min Lorry Sdn Bhd | G54: RA Norsodyne 3338NW (220Kg) | H54: 1 | I54: =VLOOKUP(F54,'Set up'!$A$2:$C$70,3,FALSE) -> 120 | J54: =VLOOKUP(F54,'Set up'!$A$2:$D$70,4,FALSE) -> 120 | K54: =A54+J54 -> 44211 | L54: =MONTH(K54) -> 1 | M54: =YEAR(K54) -> 2021 | N54: 1254 | O54: =SUM(-N54) -> -1254 | P54: =SUM(N54+O54) -> 0 | Q54: =SUM(Q53+N54) -> 63496.7 | R54: =VLOOKUP(F54,'Set up'!$A$2:$E$70,5,FALSE) -> Chq | S54: PD HLB 004649, 25/1/2021
A55: 44091 | B55: =MONTH(A55) -> 9 | C55: =YEAR(A55) -> 2020 | D55: INV2020/00000027 | E55: =VLOOKUP(F55,'Set up'!$A$2:$C$70,2,FALSE) -> C00000004 | F55: Siew Min Lorry Sdn Bhd | G55: RA CSM 450 GSM 54kg 64m(L) X 1860mm(W) | H55: 3 | I55: =VLOOKUP(F55,'Set up'!$A$2:$C$70,3,FALSE) -> 120 | J55: =VLOOKUP(F55,'Set up'!$A$2:$D$70,4,FALSE) -> 120 | K55: =A55+J55 -> 44211 | L55: =MONTH(K55) -> 1 | M55: =YEAR(K55) -> 2021 | N55: 874.8 | O55: =SUM(-N55) -> -874.8 | P55: =SUM(N55+O55) -> 0 | Q55: =SUM(Q54+N55) -> 64371.5 | R55: =VLOOKUP(F55,'Set up'!$A$2:$E$70,5,FALSE) -> Chq | S55: PD HLB 004649, 25/1/2021
A56: 44091 | B56: =MONTH(A56) -> 9 | C56: =YEAR(A56) -> 2020 | D56: INV2020/00000027 | E56: =VLOOKUP(F56,'Set up'!$A$2:$C$70,2,FALSE) -> C00000004 | F56: Siew Min Lorry Sdn Bhd | G56: RA CSM 300 GSM 54Kg 96m(L) X 1860mm(W) | H56: 3 | I56: =VLOOKUP(F56,'Set up'!$A$2:$C$70,3,FALSE) -> 120 | J56: =VLOOKUP(F56,'Set up'!$A$2:$D$70,4,FALSE) -> 120 | K56: =A56+J56 -> 44211 | L56: =MONTH(K56) -> 1 | M56: =YEAR(K56) -> 2021 | N56: 874.8 | O56: =SUM(-N56) -> -874.8 | P56: =SUM(N56+O56) -> 0 | Q56: =SUM(Q55+N56) -> 65246.3 | R56: =VLOOKUP(F56,'Set up'!$A$2:$E$70,5,FALSE) -> Chq | S56: PD HLB 004649, 25/1/2021
A57: 44091 | B57: =MONTH(A57) -> 9 | C57: =YEAR(A57) -> 2020 | D57: INV2020/00000027 | E57: =VLOOKUP(F57,'Set up'!$A$2:$C$70,2,FALSE) -> C00000004 | F57: Siew Min Lorry Sdn Bhd | G57: RA Gelcoat GP-H (20kg) | H57: 6 | I57: =VLOOKUP(F57,'Set up'!$A$2:$C$70,3,FALSE) -> 120 | J57: =VLOOKUP(F57,'Set up'!$A$2:$D$70,4,FALSE) -> 120 | K57: =A57+J57 -> 44211 | L57: =MONTH(K57) -> 1 | M57: =YEAR(K57) -> 2021 | N57: 1224 | O57: =SUM(-N57) -> -1224 | P57: =SUM(N57+O57) -> 0 | Q57: =SUM(Q56+N57) -> 66470.3 | R57: =VLOOKUP(F57,'Set up'!$A$2:$E$70,5,FALSE) -> Chq | S57: PD HLB 004649, 25/1/2021
A58: 44091 | B58: =MONTH(A58) -> 9 | C58: =YEAR(A58) -> 2020 | D58: INV2020/00000027 | E58: =VLOOKUP(F58,'Set up'!$A$2:$C$70,2,FALSE) -> C00000004 | F58: Siew Min Lorry Sdn Bhd | G58: RA Butanox M50 (5kg) | H58: 4 | I58: =VLOOKUP(F58,'Set up'!$A$2:$C$70,3,FALSE) -> 120 | J58: =VLOOKUP(F58,'Set up'!$A$2:$D$70,4,FALSE) -> 120 | K58: =A58+J58 -> 44211 | L58: =MONTH(K58) -> 1 | M58: =YEAR(K58) -> 2021 | N58: 360 | O58: =SUM(-N58) -> -360 | P58: =SUM(N58+O58) -> 0 | Q58: =SUM(Q57+N58) -> 66830.3 | R58: =VLOOKUP(F58,'Set up'!$A$2:$E$70,5,FALSE) -> Chq | S58: PD HLB 004649, 25/1/2021
A59: 44091 | B59: =MONTH(A59) -> 9 | C59: =YEAR(A59) -> 2020 | D59: INV2020/00000027 | E59: =VLOOKUP(F59,'Set up'!$A$2:$C$70,2,FALSE) -> C00000004 | F59: Siew Min Lorry Sdn Bhd | G59: RA Accelerator (5kg) | H59: 1 | I59: =VLOOKUP(F59,'Set up'!$A$2:$C$70,3,FALSE) -> 120 | J59: =VLOOKUP(F59,'Set up'!$A$2:$D$70,4,FALSE) -> 120 | K59: =A59+J59 -> 44211 | L59: =MONTH(K59) -> 1 | M59: =YEAR(K59) -> 2021 | N59: 390 | O59: =SUM(-N59) -> -390 | P59: =SUM(N59+O59) -> 0 | Q59: =SUM(Q58+N59) -> 67220.3 | R59: =VLOOKUP(F59,'Set up'!$A$2:$E$70,5,FALSE) -> Chq | S59: PD HLB 004649, 25/1/2021
A60: 44091 | B60: =MONTH(A60) -> 9 | C60: =YEAR(A60) -> 2020 | D60: INV2020/00000028 | E60: =VLOOKUP(F60,'Set up'!$A$2:$C$70,2,FALSE) -> C00000001 | F60: Kelnico Marketing | G60: RA Resin 3317AW (220Kg) | H60: 1 | I60: =VLOOKUP(F60,'Set up'!$A$2:$C$70,3,FALSE) -> Cash | J60: =VLOOKUP(F60,'Set up'!$A$2:$D$70,4,FALSE) -> 0 | K60: =A60+J60 -> 44091 | L60: =MONTH(K60) -> 9 | M60: =YEAR(K60) -> 2020 | N60: 1496 | O60: =SUM(-N60) -> -1496 | P60: =SUM(N60+O60) -> 0 | Q60: =SUM(Q59+N60) -> 68716.3 | R60: =VLOOKUP(F60,'Set up'!$A$2:$E$70,5,FALSE) -> Trsf | S60: Trst 22/9/2020
A61: 44091 | B61: =MONTH(A61) -> 9 | C61: =YEAR(A61) -> 2020 | D61: INV2020/00000028 | E61: =VLOOKUP(F61,'Set up'!$A$2:$C$70,2,FALSE) -> C00000001 | F61: Kelnico Marketing | G61: RA CSM 450 GSM JUSHI 37kg 79m(L) X 1040mm(W) | H61: 2 | I61: =VLOOKUP(F61,'Set up'!$A$2:$C$70,3,FALSE) -> Cash | J61: =VLOOKUP(F61,'Set up'!$A$2:$D$70,4,FALSE) -> 0 | K61: =A61+J61 -> 44091 | L61: =MONTH(K61) -> 9 | M61: =YEAR(K61) -> 2020 | N61: 481 | O61: =SUM(-N61) -> -481 | P61: =SUM(N61+O61) -> 0 | Q61: =SUM(Q60+N61) -> 69197.3 | R61: =VLOOKUP(F61,'Set up'!$A$2:$E$70,5,FALSE) -> Trsf | S61: Trst 22/9/2020
A62: 44096 | B62: =MONTH(A62) -> 9 | C62: =YEAR(A62) -> 2020 | D62: INV2020/00000029 | E62: =VLOOKUP(F62,'Set up'!$A$2:$C$70,2,FALSE) -> C00000004 | F62: Siew Min Lorry Sdn Bhd | G62: RA Nor 3338W (220Kg) | H62: 5 | I62: =VLOOKUP(F62,'Set up'!$A$2:$C$70,3,FALSE) -> 120 | J62: =VLOOKUP(F62,'Set up'!$A$2:$D$70,4,FALSE) -> 120 | K62: =A62+J62 -> 44216 | L62: =MONTH(K62) -> 1 | M62: =YEAR(K62) -> 2021 | N62: 6270 | O62: =SUM(-N62) -> -6270 | P62: =SUM(N62+O62) -> 0 | Q62: =SUM(Q61+N62) -> 75467.3 | R62: =VLOOKUP(F62,'Set up'!$A$2:$E$70,5,FALSE) -> Chq | S62: PD HLB 004649, 25/1/2021
... A86: 44116 | B86: =MONTH(A86) -> 10 | C86: =YEAR(A86) -> 2020 | D86: INV2020/00000037 | E86: =VLOOKUP(F86,'Set up'!$A$2:$C$70,2,FALSE) -> C00000001 | F86: Kelnico Marketing | G86: RA CSM 450 GSM JUSHI 37kg 79m(L) X 1040mm(W) | H86: 4 | I86: =VLOOKUP(F86,'Set up'!$A$2:$C$70,3,FALSE) -> Cash | J86: =VLOOKUP(F86,'Set up'!$A$2:$D$70,4,FALSE) -> 0 | K86: =A86+J86 -> 44116 | L86: =MONTH(K86) -> 10 | M86: =YEAR(K86) -> 2020 | N86: 962 | O86: =SUM(-N86) -> -962 | P86: =SUM(N86+O86) -> 0 | Q86: =SUM(Q85+N86) -> 120877.3 | R86: =VLOOKUP(F86,'Set up'!$A$2:$E$70,5,FALSE) -> Trsf | S86: Trsf 19/10/2020
A87: 44118 | B87: =MONTH(A87) -> 10 | C87: =YEAR(A87) -> 2020 | D87: INV2020/00000038 | E87: =VLOOKUP(F87,'Set up'!$A$2:$C$70,2,FALSE) -> C00000007 | F87: Chin Fibreglass (M) Sdn Bhd | G87: RA Gelcoat GP-H (20kg) | H87: 7 | I87: =VLOOKUP(F87,'Set up'!$A$2:$C$70,3,FALSE) -> Cash | J87: =VLOOKUP(F87,'Set up'!$A$2:$D$70,4,FALSE) -> 0 | K87: =A87+J87 -> 44118 | L87: =MONTH(K87) -> 10 | M87: =YEAR(K87) -> 2020 | N87: 1470 | O87: -1470 | P87: =SUM(N87+O87) -> 0 | Q87: =SUM(Q86+N87) -> 122347.3 | R87: =VLOOKUP(F87,'Set up'!$A$2:$E$70,5,FALSE) -> Trsf | S87: Due 30/11/2020
A88: 44118 | B88: =MONTH(A88) -> 10 | C88: =YEAR(A88) -> 2020 | D88: INV2020/00000038 | E88: =VLOOKUP(F88,'Set up'!$A$2:$C$70,2,FALSE) -> C00000007 | F88: Chin Fibreglass (M) Sdn Bhd | G88: RA Butanox M50 (5kg) | H88: 8 | I88: =VLOOKUP(F88,'Set up'!$A$2:$C$70,3,FALSE) -> Cash | J88: =VLOOKUP(F88,'Set up'!$A$2:$D$70,4,FALSE) -> 0 | K88: =A88+J88 -> 44118 | L88: =MONTH(K88) -> 10 | M88: =YEAR(K88) -> 2020 | N88: 720 | O88: -720 | P88: =SUM(N88+O88) -> 0 | Q88: =SUM(Q87+N88) -> 123067.3 | R88: =VLOOKUP(F88,'Set up'!$A$2:$E$70,5,FALSE) -> Trsf | S88: Due 30/11/2020
A89: 44123 | B89: =MONTH(A89) -> 10 | C89: =YEAR(A89) -> 2020 | D89: INV2020/00000038 | E89: =VLOOKUP(F89,'Set up'!$A$2:$C$70,2,FALSE) -> C00000007 | F89: Chin Fibreglass (M) Sdn Bhd | G89: RA Gelcoat GS-H (20kg) | H89: 2 | I89: =VLOOKUP(F89,'Set up'!$A$2:$C$70,3,FALSE) -> Cash | J89: =VLOOKUP(F89,'Set up'!$A$2:$D$70,4,FALSE) -> 0 | K89: =A89+J89 -> 44123 | L89: =MONTH(K89) -> 10 | M89: =YEAR(K89) -> 2020 | N89: 460 | O89: -460 | P89: =SUM(N89+O89) -> 0 | Q89: =SUM(Q88+N89) -> 123527.3 | R89: =VLOOKUP(F89,'Set up'!$A$2:$E$70,5,FALSE) -> Trsf | S89: Due 30/11/2020
A90: 44121 | B90: =MONTH(A90) -> 10 | C90: =YEAR(A90) -> 2020 | D90: INV2020/00000039 | E90: =VLOOKUP(F90,'Set up'!$A$2:$C$70,2,FALSE) -> C00000003 | F90: Pandian Art Gallery Manufacturing | G90: RA Mirror Glaze | H90: 4 | I90: =VLOOKUP(F90,'Set up'!$A$2:$C$70,3,FALSE) -> 45 | J90: =VLOOKUP(F90,'Set up'!$A$2:$D$70,4,FALSE) -> 45 | K90: =A90+J90 -> 44166 | L90: =MONTH(K90) -> 12 | M90: =YEAR(K90) -> 2020 | N90: 180 | O90: =SUM(-N90) -> -180 | P90: =SUM(N90+O90) -> 0 | Q90: =SUM(Q89+N90) -> 123707.3 | R90: =VLOOKUP(F90,'Set up'!$A$2:$E$70,5,FALSE) -> PD Chq | S90: PD Chq 22/10, RM384/-
A91: 44121 | B91: =MONTH(A91) -> 10 | C91: =YEAR(A91) -> 2020 | D91: INV2020/00000040 | E91: =VLOOKUP(F91,'Set up'!$A$2:$C$70,2,FALSE) -> C00000003 | F91: Pandian Art Gallery Manufacturing | G91: RA CSM 300 GSM TWL 30kg 64m(L) x 1040mm(W) | H91: 1 | I91: =VLOOKUP(F91,'Set up'!$A$2:$C$70,3,FALSE) -> 45 | J91: =VLOOKUP(F91,'Set up'!$A$2:$D$70,4,FALSE) -> 45 | K91: =A91+J91 -> 44166 | L91: =MONTH(K91) -> 12 | M91: =YEAR(K91) -> 2020 | N91: 204 | O91: =SUM(-N91) -> -204 | P91: =SUM(N91+O91) -> 0 | Q91: =SUM(Q90+N91) -> 123911.3 | R91: =VLOOKUP(F91,'Set up'!$A$2:$E$70,5,FALSE) -> PD Chq | S91: PD Chq 22/10, RM384/-
A92: 44123 | B92: =MONTH(A92) -> 10 | C92: =YEAR(A92) -> 2020 | D92: INV2020/00000041 | E92: =VLOOKUP(F92,'Set up'!$A$2:$C$70,2,FALSE) -> C00000001 | F92: Kelnico Marketing | G92: RA Gelcoat GS-S ISO (20kg) | H92: 4 | I92: =VLOOKUP(F92,'Set up'!$A$2:$C$70,3,FALSE) -> Cash | J92: =VLOOKUP(F92,'Set up'!$A$2:$D$70,4,FALSE) -> 0 | K92: =A92+J92 -> 44123 | L92: =MONTH(K92) -> 10 | M92: =YEAR(K92) -> 2020 | N92: 960 | O92: =SUM(-N92) -> -960 | P92: =SUM(N92+O92) -> 0 | Q92: =SUM(Q91+N92) -> 124871.3 | R92: =VLOOKUP(F92,'Set up'!$A$2:$E$70,5,FALSE) -> Trsf | S92: Trsf 9/11/2020
A93: 44123 | B93: =MONTH(A93) -> 10 | C93: =YEAR(A93) -> 2020 | D93: INV2020/00000041 | E93: =VLOOKUP(F93,'Set up'!$A$2:$C$70,2,FALSE) -> C00000001 | F93: Kelnico Marketing | G93: RA Pigment Super White (25Kg) | H93: 1 | I93: =VLOOKUP(F93,'Set up'!$A$2:$C$70,3,FALSE) -> Cash | J93: =VLOOKUP(F93,'Set up'!$A$2:$D$70,4,FALSE) -> 0 | K93: =A93+J93 -> 44123 | L93: =MONTH(K93) -> 10 | M93: =YEAR(K93) -> 2020 | N93: 625 | O93: =SUM(-N93) -> -625 | P93: =SUM(N93+O93) -> 0 | Q93: =SUM(Q92+N93) -> 125496.3 | R93: =VLOOKUP(F93,'Set up'!$A$2:$E$70,5,FALSE) -> Trsf | S93: Trsf 9/11/2020
A94: 44123 | B94: =MONTH(A94) -> 10 | C94: =YEAR(A94) -> 2020 | D94: INV2020/00000041 | E94: =VLOOKUP(F94,'Set up'!$A$2:$C$70,2,FALSE) -> C00000001 | F94: Kelnico Marketing | G94: Brush 2 1/2" (12 pc) | H94: 1 | I94: =VLOOKUP(F94,'Set up'!$A$2:$C$70,3,FALSE) -> Cash | J94: =VLOOKUP(F94,'Set up'!$A$2:$D$70,4,FALSE) -> 0 | K94: =A94+J94 -> 44123 | L94: =MONTH(K94) -> 10 | M94: =YEAR(K94) -> 2020 | N94: 60 | O94: =SUM(-N94) -> -60 | P94: =SUM(N94+O94) -> 0 | Q94: =SUM(Q93+N94) -> 125556.3 | R94: =VLOOKUP(F94,'Set up'!$A$2:$E$70,5,FALSE) -> Trsf | S94: Trsf 9/11/2020
A95: 44123 | B95: =MONTH(A95) -> 10 | C95: =YEAR(A95) -> 2020 | D95: INV2020/00000042 | E95: =VLOOKUP(F95,'Set up'!$A$2:$C$70,2,FALSE) -> C00000005 | F95: Artscene Creative | G95: RA Butanox M50 (5kg) | H95: 1 | I95: =VLOOKUP(F95,'Set up'!$A$2:$C$70,3,FALSE) -> Cash | J95: =VLOOKUP(F95,'Set up'!$A$2:$D$70,4,FALSE) -> 0 | K95: =A95+J95 -> 44123 | L95: =MONTH(K95) -> 10 | M95: =YEAR(K95) -> 2020 | N95: 90 | O95: =SUM(-N95) -> -90 | P95: =SUM(N95+O95) -> 0 | Q95: =SUM(Q94+N95) -> 125646.3 | R95: =VLOOKUP(F95,'Set up'!$A$2:$E$70,5,FALSE) -> Chq | S95: Chq CIMB 000054 28/10/2019
A96: 44125 | B96: =MONTH(A96) -> 10 | C96: =YEAR(A96) -> 2020 | D96: INV2020/00000043 | E96: =VLOOKUP(F96,'Set up'!$A$2:$C$70,2,FALSE) -> C00000005 | F96: Artscene Creative | G96: RA Resin 3317AW (220Kg) | H96: 1 | I96: =VLOOKUP(F96,'Set up'!$A$2:$C$70,3,FALSE) -> Cash | J96: =VLOOKUP(F96,'Set up'!$A$2:$D$70,4,FALSE) -> 0 | K96: =A96+J96 -> 44125 | L96: =MONTH(K96) -> 10 | M96: =YEAR(K96) -> 2020 | N96: 1496 | O96: =SUM(-N96) -> -1496 | P96: =SUM(N96+O96) -> 0 | Q96: =SUM(Q95+N96) -> 127142.3 | R96: =VLOOKUP(F96,'Set up'!$A$2:$E$70,5,FALSE) -> Chq | S96: Chq CIMB 000050 21/10/2020
A97: 44125 | B97: =MONTH(A97) -> 10 | C97: =YEAR(A97) -> 2020 | D97: INV2020/00000044 | E97: =VLOOKUP(F97,'Set up'!$A$2:$C$70,2,FALSE) -> C00000010 | F97: Yew Seng Gardening Supply Sdn Bhd | G97: RA Nor 3338W (220Kg) | H97: 5 | I97: =VLOOKUP(F97,'Set up'!$A$2:$C$70,3,FALSE) -> 120 | J97: =VLOOKUP(F97,'Set up'!$A$2:$D$70,4,FALSE) -> 120 | K97: =A97+J97 -> 44245 | L97: =MONTH(K97) -> 2 | M97: =YEAR(K97) -> 2021 | N97: 6600 | O97: =SUM(-N97) -> -6600 | P97: =SUM(N97+O97) -> 0 | Q97: =SUM(Q96+N97) -> 133742.3 | R97: =VLOOKUP(F97,'Set up'!$A$2:$E$70,5,FALSE) -> Trsf | S97: Trsf 19/3/2021
A98: 44125 | B98: =MONTH(A98) -> 10 | C98: =YEAR(A98) -> 2020 | D98: INV2020/00000044 | E98: =VLOOKUP(F98,'Set up'!$A$2:$C$70,2,FALSE) -> C00000010 | F98: Yew Seng Gardening Supply Sdn Bhd | G98: RA CSM 450 GSM JUSHI 37kg 79m(L) X 1040mm(W) | H98: 4 | I98: =VLOOKUP(F98,'Set up'!$A$2:$C$70,3,FALSE) -> 120 | J98: =VLOOKUP(F98,'Set up'!$A$2:$D$70,4,FALSE) -> 120 | K98: =A98+J98 -> 44245 | L98: =MONTH(K98) -> 2 | M98: =YEAR(K98) -> 2021 | N98: 888 | O98: =SUM(-N98) -> -888 | P98: =SUM(N98+O98) -> 0 | Q98: =SUM(Q97+N98) -> 134630.3 | R98: =VLOOKUP(F98,'Set up'!$A$2:$E$70,5,FALSE) -> Trsf | S98: Trsf 19/3/2021
A99: 44125 | B99: =MONTH(A99) -> 10 | C99: =YEAR(A99) -> 2020 | D99: INV2020/00000044 | E99: =VLOOKUP(F99,'Set up'!$A$2:$C$70,2,FALSE) -> C00000010 | F99: Yew Seng Gardening Supply Sdn Bhd | G99: RA Talcum Powder (25kg) | H99: 5 | I99: =VLOOKUP(F99,'Set up'!$A$2:$C$70,3,FALSE) -> 120 | J99: =VLOOKUP(F99,'Set up'!$A$2:$D$70,4,FALSE) -> 120 | K99: =A99+J99 -> 44245 | L99: =MONTH(K99) -> 2 | M99: =YEAR(K99) -> 2021 | N99: 275 | O99: =SUM(-N99) -> -275 | P99: =SUM(N99+O99) -> 0 | Q99: =SUM(Q98+N99) -> 134905.3 | R99: =VLOOKUP(F99,'Set up'!$A$2:$E$70,5,FALSE) -> Trsf | S99: Trsf 19/3/2021
A100: 44125 | B100: =MONTH(A100) -> 10 | C100: =YEAR(A100) -> 2020 | D100: INV2020/00000044 | E100: =VLOOKUP(F100,'Set up'!$A$2:$C$70,2,FALSE) -> C00000010 | F100: Yew Seng Gardening Supply Sdn Bhd | G100: RA Butanox M50 (5kg) | H100: 4 | I100: =VLOOKUP(F100,'Set up'!$A$2:$C$70,3,FALSE) -> 120 | J100: =VLOOKUP(F100,'Set up'!$A$2:$D$70,4,FALSE) -> 120 | K100: =A100+J100 -> 44245 | L100: =MONTH(K100) -> 2 | M100: =YEAR(K100) -> 2021 | N100: 360 | O100: =SUM(-N100) -> -360 | P100: =SUM(N100+O100) -> 0 | Q100: =SUM(Q99+N100) -> 135265.3 | R100: =VLOOKUP(F100,'Set up'!$A$2:$E$70,5,FALSE) -> Trsf | S100: Trsf 19/3/2021
A101: 44130 | B101: =MONTH(A101) -> 10 | C101: =YEAR(A101) -> 2020 | D101: INV2020/00000045 | E101: =VLOOKUP(F101,'Set up'!$A$2:$C$70,2,FALSE) -> C00000003 | F101: Pandian Art Gallery Manufacturing | G101: RA Resin 3317AW (220Kg) | H101: 3 | I101: =VLOOKUP(F101,'Set up'!$A$2:$C$70,3,FALSE) -> 45 | J101: =VLOOKUP(F101,'Set up'!$A$2:$D$70,4,FALSE) -> 45 | K101: =A101+J101 -> 44175 | L101: =MONTH(K101) -> 12 | M101: =YEAR(K101) -> 2020 | N101: 4554 | O101: =SUM(-N101) -> -4554 | P101: =SUM(N101+O101) -> 0 | Q101: =SUM(Q100+N101) -> 139819.3 | R101: =VLOOKUP(F101,'Set up'!$A$2:$E$70,5,FALSE) -> PD Chq | S101: PD Chq 12/10, 19/10 & 26/10
... A123: 44155 | B123: =MONTH(A123) -> 11 | C123: =YEAR(A123) -> 2020 | D123: INV2020/00000054 | E123: =VLOOKUP(F123,'Set up'!$A$2:$C$70,2,FALSE) -> C00000010 | F123: Yew Seng Gardening Supply Sdn Bhd | G123: RA Bosny Wax (15kg) | H123: 1 | I123: =VLOOKUP(F123,'Set up'!$A$2:$C$70,3,FALSE) -> 120 | J123: =VLOOKUP(F123,'Set up'!$A$2:$D$70,4,FALSE) -> 120 | K123: =A123+J123 -> 44275 | L123: =MONTH(K123) -> 3 | M123: =YEAR(K123) -> 2021 | N123: 375 | O123: =SUM(-N123) -> -375 | P123: =SUM(N123+O123) -> 0 | Q123: =SUM(Q122+N123) -> 162845.5 | R123: =VLOOKUP(F123,'Set up'!$A$2:$E$70,5,FALSE) -> Trsf | S123: Due 28/2/2020
A124: 44156 | B124: =MONTH(A124) -> 11 | C124: =YEAR(A124) -> 2020 | D124: INV2020/00000055 | E124: =VLOOKUP(F124,'Set up'!$A$2:$C$70,2,FALSE) -> C00000008 | F124: Wonderland Design Productions Studio | G124: RA Nor 3338W (220Kg) | H124: 1 | I124: =VLOOKUP(F124,'Set up'!$A$2:$C$70,3,FALSE) -> Cash | J124: =VLOOKUP(F124,'Set up'!$A$2:$D$70,4,FALSE) -> 0 | K124: =A124+J124 -> 44156 | L124: =MONTH(K124) -> 11 | M124: =YEAR(K124) -> 2020 | N124: 1584 | O124: -1584 | P124: =SUM(N124+O124) -> 0 | Q124: =SUM(Q123+N124) -> 164429.5 | R124: =VLOOKUP(F124,'Set up'!$A$2:$E$70,5,FALSE) -> Trsf
A125: 44156 | B125: =MONTH(A125) -> 11 | C125: =YEAR(A125) -> 2020 | D125: INV2020/00000055 | E125: =VLOOKUP(F125,'Set up'!$A$2:$C$70,2,FALSE) -> C00000008 | F125: Wonderland Design Productions Studio | G125: RA Gelcoat GP-H (20kg) | H125: 2 | I125: =VLOOKUP(F125,'Set up'!$A$2:$C$70,3,FALSE) -> Cash | J125: =VLOOKUP(F125,'Set up'!$A$2:$D$70,4,FALSE) -> 0 | K125: =A125+J125 -> 44156 | L125: =MONTH(K125) -> 11 | M125: =YEAR(K125) -> 2020 | N125: 420 | O125: -420 | P125: =SUM(N125+O125) -> 0 | Q125: =SUM(Q124+N125) -> 164849.5 | R125: =VLOOKUP(F125,'Set up'!$A$2:$E$70,5,FALSE) -> Trsf
A126: 44156 | B126: =MONTH(A126) -> 11 | C126: =YEAR(A126) -> 2020 | D126: INV2020/00000055 | E126: =VLOOKUP(F126,'Set up'!$A$2:$C$70,2,FALSE) -> C00000008 | F126: Wonderland Design Productions Studio | G126: RA Butanox M50 (5kg) | H126: 1 | I126: =VLOOKUP(F126,'Set up'!$A$2:$C$70,3,FALSE) -> Cash | J126: =VLOOKUP(F126,'Set up'!$A$2:$D$70,4,FALSE) -> 0 | K126: =A126+J126 -> 44156 | L126: =MONTH(K126) -> 11 | M126: =YEAR(K126) -> 2020 | N126: 90 | O126: -90 | P126: =SUM(N126+O126) -> 0 | Q126: =SUM(Q125+N126) -> 164939.5 | R126: =VLOOKUP(F126,'Set up'!$A$2:$E$70,5,FALSE) -> Trsf
A127: 44156 | B127: =MONTH(A127) -> 11 | C127: =YEAR(A127) -> 2020 | D127: INV2020/00000055 | E127: =VLOOKUP(F127,'Set up'!$A$2:$C$70,2,FALSE) -> C00000008 | F127: Wonderland Design Productions Studio | G127: RA CSM 450 GSM JUSHI 37kg 79m(L) X 1040mm(W) | H127: 2 | I127: =VLOOKUP(F127,'Set up'!$A$2:$C$70,3,FALSE) -> Cash | J127: =VLOOKUP(F127,'Set up'!$A$2:$D$70,4,FALSE) -> 0 | K127: =A127+J127 -> 44156 | L127: =MONTH(K127) -> 11 | M127: =YEAR(K127) -> 2020 | N127: 518 | O127: -518 | P127: =SUM(N127+O127) -> 0 | Q127: =SUM(Q126+N127) -> 165457.5 | R127: =VLOOKUP(F127,'Set up'!$A$2:$E$70,5,FALSE) -> Trsf
A128: 44158 | B128: =MONTH(A128) -> 11 | C128: =YEAR(A128) -> 2020 | D128: INV2020/00000056 | E128: =VLOOKUP(F128,'Set up'!$A$2:$C$70,2,FALSE) -> C00000005 | F128: Artscene Creative | G128: RA Resin 3317AW (220Kg) | H128: 1 | I128: =VLOOKUP(F128,'Set up'!$A$2:$C$70,3,FALSE) -> Cash | J128: =VLOOKUP(F128,'Set up'!$A$2:$D$70,4,FALSE) -> 0 | K128: =A128+J128 -> 44158 | L128: =MONTH(K128) -> 11 | M128: =YEAR(K128) -> 2020 | N128: 1540 | O128: =SUM(-N128) -> -1540 | P128: =SUM(N128+O128) -> 0 | Q128: =SUM(Q127+N128) -> 166997.5 | R128: =VLOOKUP(F128,'Set up'!$A$2:$E$70,5,FALSE) -> Chq | S128: Chq CIMB 000060 24/11/20, Banked in 30/11/20
A129: 44159 | B129: =MONTH(A129) -> 11 | C129: =YEAR(A129) -> 2020 | D129: INV2020/00000057 | E129: =VLOOKUP(F129,'Set up'!$A$2:$C$70,2,FALSE) -> C00000011 | F129: JT Johan Sdn Bhd | G129: Alkaline resistance Chopped Strand 24MM (18Kgs) | H129: 3 | I129: =VLOOKUP(F129,'Set up'!$A$2:$C$70,3,FALSE) -> Cash | J129: =VLOOKUP(F129,'Set up'!$A$2:$D$70,4,FALSE) -> 0 | K129: =A129+J129 -> 44159 | L129: =MONTH(K129) -> 11 | M129: =YEAR(K129) -> 2020 | N129: 982.8 | O129: =SUM(-N129) -> -982.8 | P129: =SUM(N129+O129) -> 0 | Q129: =SUM(Q128+N129) -> 167980.3 | R129: =VLOOKUP(F129,'Set up'!$A$2:$E$70,5,FALSE) -> Trsf | S129: Trsf 23/11/2020
A130: 44159 | B130: =MONTH(A130) -> 11 | C130: =YEAR(A130) -> 2020 | D130: INV2020/00000057 | E130: =VLOOKUP(F130,'Set up'!$A$2:$C$70,2,FALSE) -> C00000011 | F130: JT Johan Sdn Bhd | G130: Transport charge | H130: 1 | I130: =VLOOKUP(F130,'Set up'!$A$2:$C$70,3,FALSE) -> Cash | J130: =VLOOKUP(F130,'Set up'!$A$2:$D$70,4,FALSE) -> 0 | K130: =A130+J130 -> 44159 | L130: =MONTH(K130) -> 11 | M130: =YEAR(K130) -> 2020 | N130: 100 | O130: =SUM(-N130) -> -100 | P130: =SUM(N130+O130) -> 0 | Q130: =SUM(Q129+N130) -> 168080.3 | R130: =VLOOKUP(F130,'Set up'!$A$2:$E$70,5,FALSE) -> Trsf | S130: Trsf 23/11/2020
A131: 44159 | B131: =MONTH(A131) -> 11 | C131: =YEAR(A131) -> 2020 | D131: INV2020/00000058 | E131: =VLOOKUP(F131,'Set up'!$A$2:$C$70,2,FALSE) -> C00000003 | F131: Pandian Art Gallery Manufacturing | G131: RA Resin 3317AW (220Kg) | H131: 1 | I131: =VLOOKUP(F131,'Set up'!$A$2:$C$70,3,FALSE) -> 45 | J131: =VLOOKUP(F131,'Set up'!$A$2:$D$70,4,FALSE) -> 45 | K131: =A131+J131 -> 44204 | L131: =MONTH(K131) -> 1 | M131: =YEAR(K131) -> 2021 | N131: 1628 | O131: =SUM(-N131) -> -1628 | P131: =SUM(N131+O131) -> 0 | Q131: =SUM(Q130+N131) -> 169708.3 | R131: =VLOOKUP(F131,'Set up'!$A$2:$E$70,5,FALSE) -> PD Chq | S131: PD Chq 10/1/21, RM2,008/-
A132: 44159 | B132: =MONTH(A132) -> 11 | C132: =YEAR(A132) -> 2020 | D132: INV2020/00000058 | E132: =VLOOKUP(F132,'Set up'!$A$2:$C$70,2,FALSE) -> C00000003 | F132: Pandian Art Gallery Manufacturing | G132: RA Talcum Powder (25Kg) | H132: 3 | I132: =VLOOKUP(F132,'Set up'!$A$2:$C$70,3,FALSE) -> 45 | J132: =VLOOKUP(F132,'Set up'!$A$2:$D$70,4,FALSE) -> 45 | K132: =A132+J132 -> 44204 | L132: =MONTH(K132) -> 1 | M132: =YEAR(K132) -> 2021 | N132: 150 | O132: =SUM(-N132) -> -150 | P132: =SUM(N132+O132) -> 0 | Q132: =SUM(Q131+N132) -> 169858.3 | R132: =VLOOKUP(F132,'Set up'!$A$2:$E$70,5,FALSE) -> PD Chq | S132: PD Chq 10/1/21, RM2,008/-
A133: 44159 | B133: =MONTH(A133) -> 11 | C133: =YEAR(A133) -> 2020 | D133: INV2020/00000058 | E133: =VLOOKUP(F133,'Set up'!$A$2:$C$70,2,FALSE) -> C00000003 | F133: Pandian Art Gallery Manufacturing | G133: RA Butanox M50 (5kg) | H133: 2 | I133: =VLOOKUP(F133,'Set up'!$A$2:$C$70,3,FALSE) -> 45 | J133: =VLOOKUP(F133,'Set up'!$A$2:$D$70,4,FALSE) -> 45 | K133: =A133+J133 -> 44204 | L133: =MONTH(K133) -> 1 | M133: =YEAR(K133) -> 2021 | N133: 185 | O133: =SUM(-N133) -> -185 | P133: =SUM(N133+O133) -> 0 | Q133: =SUM(Q132+N133) -> 170043.3 | R133: =VLOOKUP(F133,'Set up'!$A$2:$E$70,5,FALSE) -> PD Chq | S133: PD Chq 10/1/21, RM2,008/-
A134: 44159 | B134: =MONTH(A134) -> 11 | C134: =YEAR(A134) -> 2020 | D134: INV2020/00000058 | E134: =VLOOKUP(F134,'Set up'!$A$2:$C$70,2,FALSE) -> C00000003 | F134: Pandian Art Gallery Manufacturing | G134: RA Miracle Gloss Wax | H134: 1 | I134: =VLOOKUP(F134,'Set up'!$A$2:$C$70,3,FALSE) -> 45 | J134: =VLOOKUP(F134,'Set up'!$A$2:$D$70,4,FALSE) -> 45 | K134: =A134+J134 -> 44204 | L134: =MONTH(K134) -> 1 | M134: =YEAR(K134) -> 2021 | N134: 45 | O134: =SUM(-N134) -> -45 | P134: =SUM(N134+O134) -> 0 | Q134: =SUM(Q133+N134) -> 170088.3 | R134: =VLOOKUP(F134,'Set up'!$A$2:$E$70,5,FALSE) -> PD Chq | S134: PD Chq 10/1/21, RM2,008/-
A135: 44162 | B135: =MONTH(A135) -> 11 | C135: =YEAR(A135) -> 2020 | D135: INV2020/00000059 | E135: =VLOOKUP(F135,'Set up'!$A$2:$C$70,2,FALSE) -> C00000001 | F135: Kelnico Marketing | G135: RA Nor 3338W (220Kg) | H135: 1 | I135: =VLOOKUP(F135,'Set up'!$A$2:$C$70,3,FALSE) -> Cash | J135: =VLOOKUP(F135,'Set up'!$A$2:$D$70,4,FALSE) -> 0 | K135: =A135+J135 -> 44162 | L135: =MONTH(K135) -> 11 | M135: =YEAR(K135) -> 2020 | N135: 1584 | O135: =SUM(-N135) -> -1584 | P135: =SUM(N135+O135) -> 0 | Q135: =SUM(Q134+N135) -> 171672.3 | R135: =VLOOKUP(F135,'Set up'!$A$2:$E$70,5,FALSE) -> Trsf | S135: Trsf 5/12/2020
A136: 44162 | B136: =MONTH(A136) -> 11 | C136: =YEAR(A136) -> 2020 | D136: INV2020/00000059 | E136: =VLOOKUP(F136,'Set up'!$A$2:$C$70,2,FALSE) -> C00000001 | F136: Kelnico Marketing | G136: RA CSM 450 GSM TWL 30kg 64m(L) X 1040mm(W) | H136: 4 | I136: =VLOOKUP(F136,'Set up'!$A$2:$C$70,3,FALSE) -> Cash | J136: =VLOOKUP(F136,'Set up'!$A$2:$D$70,4,FALSE) -> 0 | K136: =A136+J136 -> 44162 | L136: =MONTH(K136) -> 11 | M136: =YEAR(K136) -> 2020 | N136: 840 | O136: =SUM(-N136) -> -840 | P136: =SUM(N136+O136) -> 0 | Q136: =SUM(Q135+N136) -> 172512.3 | R136: =VLOOKUP(F136,'Set up'!$A$2:$E$70,5,FALSE) -> Trsf | S136: Trsf 5/12/2020
A137: 44163 | B137: =MONTH(A137) -> 11 | C137: =YEAR(A137) -> 2020 | D137: INV2020/00000060 | E137: =VLOOKUP(F137,'Set up'!$A$2:$C$70,2,FALSE) -> C00000009 | F137: JMC Steel Engineering Sdn Bhd | G137: RA Gelcoat GP-H (20kg) | H137: 2 | I137: =VLOOKUP(F137,'Set up'!$A$2:$C$70,3,FALSE) -> 60 | J137: =VLOOKUP(F137,'Set up'!$A$2:$D$70,4,FALSE) -> 60 | K137: =A137+J137 -> 44223 | L137: =MONTH(K137) -> 1 | M137: =YEAR(K137) -> 2021 | N137: 408 | O137: =SUM(-N137) -> -408 | P137: =SUM(N137+O137) -> 0 | Q137: =SUM(Q136+N137) -> 172920.3 | R137: =VLOOKUP(F137,'Set up'!$A$2:$E$70,5,FALSE) -> Chq | S137: Chq HL 009828, dd 6/2/21, Banked in 7/2/21
A138: 44165 | B138: =MONTH(A138) -> 11 | C138: =YEAR(A138) -> 2020 | D138: INV2020/00000061 | E138: =VLOOKUP(F138,'Set up'!$A$2:$C$70,2,FALSE) -> C00000008 | F138: Wonderland Design Productions Studio | G138: RA Gelcoat GP-H (20kg) | H138: 5 | I138: =VLOOKUP(F138,'Set up'!$A$2:$C$70,3,FALSE) -> Cash | J138: =VLOOKUP(F138,'Set up'!$A$2:$D$70,4,FALSE) -> 0 | K138: =A138+J138 -> 44165 | L138: =MONTH(K138) -> 11 | M138: =YEAR(K138) -> 2020 | N138: 1050 | O138: =SUM(-N138) -> -1050 | P138: =SUM(N138+O138) -> 0 | Q138: =SUM(Q137+N138) -> 173970.3 | R138: =VLOOKUP(F138,'Set up'!$A$2:$E$70,5,FALSE) -> Trsf
A139: 44165 | B139: =MONTH(A139) -> 11 | C139: =YEAR(A139) -> 2020 | D139: INV2020/00000062 | E139: =VLOOKUP(F139,'Set up'!$A$2:$C$70,2,FALSE) -> C00000010 | F139: Yew Seng Gardening Supply Sdn Bhd | G139: RA Nor 3338W (220Kg) | H139: 5 | I139: =VLOOKUP(F139,'Set up'!$A$2:$C$70,3,FALSE) -> 120 | J139: =VLOOKUP(F139,'Set up'!$A$2:$D$70,4,FALSE) -> 120 | K139: =A139+J139 -> 44285 | L139: =MONTH(K139) -> 3 | M139: =YEAR(K139) -> 2021 | N139: 6600 | O139: =SUM(-N139) -> -6600 | P139: =SUM(N139+O139) -> 0 | Q139: =SUM(Q138+N139) -> 180570.3 | R139: =VLOOKUP(F139,'Set up'!$A$2:$E$70,5,FALSE) -> Trsf | S139: Due 28/2/2020
A140: 44165 | B140: =MONTH(A140) -> 11 | C140: =YEAR(A140) -> 2020 | D140: INV2020/00000062 | E140: =VLOOKUP(F140,'Set up'!$A$2:$C$70,2,FALSE) -> C00000010 | F140: Yew Seng Gardening Supply Sdn Bhd | G140: RA CSM 450 GSM TWL 30kg 64m(L) X 1040mm(W) | H140: 4 | I140: =VLOOKUP(F140,'Set up'!$A$2:$C$70,3,FALSE) -> 120 | J140: =VLOOKUP(F140,'Set up'!$A$2:$D$70,4,FALSE) -> 120 | K140: =A140+J140 -> 44285 | L140: =MONTH(K140) -> 3 | M140: =YEAR(K140) -> 2021 | N140: 720 | O140: =SUM(-N140) -> -720 | P140: =SUM(N140+O140) -> 0 | Q140: =SUM(Q139+N140) -> 181290.3 | R140: =VLOOKUP(F140,'Set up'!$A$2:$E$70,5,FALSE) -> Trsf | S140: Due 28/2/2020
A141: 44165 | B141: =MONTH(A141) -> 11 | C141: =YEAR(A141) -> 2020 | D141: INV2020/00000062 | E141: =VLOOKUP(F141,'Set up'!$A$2:$C$70,2,FALSE) -> C00000010 | F141: Yew Seng Gardening Supply Sdn Bhd | G141: RA Talcum Powder (25kg) | H141: 5 | I141: =VLOOKUP(F141,'Set up'!$A$2:$C$70,3,FALSE) -> 120 | J141: =VLOOKUP(F141,'Set up'!$A$2:$D$70,4,FALSE) -> 120 | K141: =A141+J141 -> 44285 | L141: =MONTH(K141) -> 3 | M141: =YEAR(K141) -> 2021 | N141: 275 | O141: =SUM(-N141) -> -275 | P141: =SUM(N141+O141) -> 0 | Q141: =SUM(Q140+N141) -> 181565.3 | R141: =VLOOKUP(F141,'Set up'!$A$2:$E$70,5,FALSE) -> Trsf | S141: Due 28/2/2020
A142: 44165 | B142: =MONTH(A142) -> 11 | C142: =YEAR(A142) -> 2020 | D142: INV2020/00000062 | E142: =VLOOKUP(F142,'Set up'!$A$2:$C$70,2,FALSE) -> C00000010 | F142: Yew Seng Gardening Supply Sdn Bhd | G142: RA Butanox M50 (5kg) | H142: 2 | I142: =VLOOKUP(F142,'Set up'!$A$2:$C$70,3,FALSE) -> 120 | J142: =VLOOKUP(F142,'Set up'!$A$2:$D$70,4,FALSE) -> 120 | K142: =A142+J142 -> 44285 | L142: =MONTH(K142) -> 3 | M142: =YEAR(K142) -> 2021 | N142: 180 | O142: =SUM(-N142) -> -180 | P142: =SUM(N142+O142) -> 0 | Q142: =SUM(Q141+N142) -> 181745.3 | R142: =VLOOKUP(F142,'Set up'!$A$2:$E$70,5,FALSE) -> Trsf | S142: Due 28/2/2020
A143: 44165 | B143: =MONTH(A143) -> 11 | C143: =YEAR(A143) -> 2020 | D143: INV2020/00000063 | E143: =VLOOKUP(F143,'Set up'!$A$2:$C$70,2,FALSE) -> C00000010 | F143: Yew Seng Gardening Supply Sdn Bhd | G143: RA Talcum Powder (25kg) | H143: 5 | I143: =VLOOKUP(F143,'Set up'!$A$2:$C$70,3,FALSE) -> 120 | J143: =VLOOKUP(F143,'Set up'!$A$2:$D$70,4,FALSE) -> 120 | K143: =A143+J143 -> 44285 | L143: =MONTH(K143) -> 3 | M143: =YEAR(K143) -> 2021 | N143: 275 | O143: =SUM(-N143) -> -275 | P143: =SUM(N143+O143) -> 0 | Q143: =SUM(Q142+N143) -> 182020.3 | R143: =VLOOKUP(F143,'Set up'!$A$2:$E$70,5,FALSE) -> Trsf | S143: Due 28/2/2020
A144: 44170 | B144: =MONTH(A144) -> 12 | C144: =YEAR(A144) -> 2020 | D144: INV2020/00000064 | E144: =VLOOKUP(F144,'Set up'!$A$2:$C$70,2,FALSE) -> #N/A | F144: Cash - Muhammad Syahin Bin | G144: RA CSM 450 GSM 54kg 64m(L) X 1860mm(W) | H144: 2 | I144: =VLOOKUP(F144,'Set up'!$A$2:$C$70,3,FALSE) -> #N/A | J144: =VLOOKUP(F144,'Set up'!$A$2:$D$70,4,FALSE) -> #N/A | K144: =A144+J144 -> #N/A | L144: =MONTH(K144) -> #N/A | M144: =YEAR(K144) -> #N/A | N144: 799.2 | O144: =SUM(-N144) -> -799.2 | P144: =SUM(N144+O144) -> 0 | Q144: =SUM(Q143+N144) -> 182819.5 | R144: =VLOOKUP(F144,'Set up'!$A$2:$E$70,5,FALSE) -> #N/A | S144: Trsf 5/12/2020
A145: 44180 | B145: =MONTH(A145) -> 12 | C145: =YEAR(A145) -> 2020 | D145: INV2020/00000065 | E145: =VLOOKUP(F145,'Set up'!$A$2:$C$70,2,FALSE) -> C00000001 | F145: Kelnico Marketing | G145: RA Resin 3317AW (220Kg) | H145: 1 | I145: =VLOOKUP(F145,'Set up'!$A$2:$C$70,3,FALSE) -> Cash | J145: =VLOOKUP(F145,'Set up'!$A$2:$D$70,4,FALSE) -> 0 | K145: =A145+J145 -> 44180 | L145: =MONTH(K145) -> 12 | M145: =YEAR(K145) -> 2020 | N145: 1716 | O145: =SUM(-N145) -> -1716 | P145: =SUM(N145+O145) -> 0 | Q145: =SUM(Q144+N145) -> 184535.5 | R145: =VLOOKUP(F145,'Set up'!$A$2:$E$70,5,FALSE) -> Trsf | S145: Trsf 18/12/2020
A146: 44180 | B146: =MONTH(A146) -> 12 | C146: =YEAR(A146) -> 2020 | D146: INV2020/00000065 | E146: =VLOOKUP(F146,'Set up'!$A$2:$C$70,2,FALSE) -> C00000001 | F146: Kelnico Marketing | G146: RA Gelcoat GS-S ISO (20kg) | H146: 2 | I146: =VLOOKUP(F146,'Set up'!$A$2:$C$70,3,FALSE) -> Cash | J146: =VLOOKUP(F146,'Set up'!$A$2:$D$70,4,FALSE) -> 0 | K146: =A146+J146 -> 44180 | L146: =MONTH(K146) -> 12 | M146: =YEAR(K146) -> 2020 | N146: 512 | O146: =SUM(-N146) -> -512 | P146: =SUM(N146+O146) -> 0 | Q146: =SUM(Q145+N146) -> 185047.5 | R146: =VLOOKUP(F146,'Set up'!$A$2:$E$70,5,FALSE) -> Trsf | S146: Trsf 18/12/2020
A147: 44191 | B147: =MONTH(A147) -> 12 | C147: =YEAR(A147) -> 2020 | D147: INV2020/00000066 | E147: =VLOOKUP(F147,'Set up'!$A$2:$C$70,2,FALSE) -> C00000004 | F147: Siew Min Lorry Sdn Bhd | G147: RA Norsodyne 3338NW (220Kg) | H147: 2 | I147: =VLOOKUP(F147,'Set up'!$A$2:$C$70,3,FALSE) -> 120 | J147: =VLOOKUP(F147,'Set up'!$A$2:$D$70,4,FALSE) -> 120 | K147: =A147+J147 -> 44311 | L147: =MONTH(K147) -> 4 | M147: =YEAR(K147) -> 2021 | N147: 2860 | O147: =SUM(-N147) -> -2860 | P147: =SUM(N147+O147) -> 0 | Q147: =SUM(Q146+N147) -> 187907.5 | R147: =VLOOKUP(F147,'Set up'!$A$2:$E$70,5,FALSE) -> Chq | S147: HL005820, 200321 (clear on 30/3/2021)
A148: 44195 | B148: =MONTH(A148) -> 12 | C148: =YEAR(A148) -> 2020 | D148: INV2020/00000067 | E148: =VLOOKUP(F148,'Set up'!$A$2:$C$70,2,FALSE) -> C00000003 | F148: Pandian Art Gallery Manufacturing | G148: RA Resin 3317AW (220Kg) | H148: 3 | I148: =VLOOKUP(F148,'Set up'!$A$2:$C$70,3,FALSE) -> 45 | J148: =VLOOKUP(F148,'Set up'!$A$2:$D$70,4,FALSE) -> 45 | K148: =A148+J148 -> 44240 | L148: =MONTH(K148) -> 2 | M148: =YEAR(K148) -> 2021 | N148: 5148 | O148: =SUM(-N148) -> -5148 | Q148: =SUM(Q147+N148) -> 193055.5 | R148: =VLOOKUP(F148,'Set up'!$A$2:$E$70,5,FALSE) -> PD Chq | S148: PD Chq 13/2, 16/2, 20/2, 27/2 (RM1,500.00, RM1,608.00, RM1,500.00 & RM1,500.00)
A149: 44195 | B149: =MONTH(A149) -> 12 | C149: =YEAR(A149) -> 2020 | D149: INV2020/00000067 | E149: =VLOOKUP(F149,'Set up'!$A$2:$C$70,2,FALSE) -> C00000003 | F149: Pandian Art Gallery Manufacturing | G149: RA CSM 450 GSM 54kg 64m(L) X 1860mm(W) | H149: 1 | I149: =VLOOKUP(F149,'Set up'!$A$2:$C$70,3,FALSE) -> 45 | J149: =VLOOKUP(F149,'Set up'!$A$2:$D$70,4,FALSE) -> 45 | K149: =A149+J149 -> 44240 | L149: =MONTH(K149) -> 2 | M149: =YEAR(K149) -> 2021 | N149: 405 | O149: =SUM(-N149) -> -405 | P149: =SUM(N149+O149) -> 0 | Q149: =SUM(Q148+N149) -> 193460.5 | R149: =VLOOKUP(F149,'Set up'!$A$2:$E$70,5,FALSE) -> PD Chq | S149: PD Chq 13/2, 16/2, 20/2, 27/2 (RM1,500.00, RM1,608.00, RM1,500.00 & RM1,500.00)
A150: 44195 | B150: =MONTH(A150) -> 12 | C150: =YEAR(A150) -> 2020 | D150: INV2020/00000067 | E150: =VLOOKUP(F150,'Set up'!$A$2:$C$70,2,FALSE) -> C00000003 | F150: Pandian Art Gallery Manufacturing | G150: RA Butanox M50 (5kg) | H150: 6 | I150: =VLOOKUP(F150,'Set up'!$A$2:$C$70,3,FALSE) -> 45 | J150: =VLOOKUP(F150,'Set up'!$A$2:$D$70,4,FALSE) -> 45 | K150: =A150+J150 -> 44240 | L150: =MONTH(K150) -> 2 | M150: =YEAR(K150) -> 2021 | N150: 555 | O150: =SUM(-N150) -> -555 | P150: =SUM(N150+O150) -> 0 | Q150: =SUM(Q149+N150) -> 194015.5 | R150: =VLOOKUP(F150,'Set up'!$A$2:$E$70,5,FALSE) -> PD Chq | S150: PD Chq 13/2, 16/2, 20/2, 27/2 (RM1,500.00, RM1,608.00, RM1,500.00 & RM1,500.00)
A151: 44196 | B151: =MONTH(A151) -> 12 | C151: =YEAR(A151) -> 2020 | D151: INV2020/00000068 | E151: =VLOOKUP(F151,'Set up'!$A$2:$C$70,2,FALSE) -> C00000010 | F151: Yew Seng Gardening Supply Sdn Bhd | G151: RA Norsodyne 3338W (220Kg) | H151: 5 | I151: =VLOOKUP(F151,'Set up'!$A$2:$C$70,3,FALSE) -> 120 | J151: =VLOOKUP(F151,'Set up'!$A$2:$D$70,4,FALSE) -> 120 | K151: =A151+J151 -> 44316 | L151: =MONTH(K151) -> 4 | M151: =YEAR(K151) -> 2021 | N151: 7700 | O151: =SUM(-N151) -> -7700 | P151: =SUM(N151+O151) -> 0 | Q151: =SUM(Q150+N151) -> 201715.5 | R151: =VLOOKUP(F151,'Set up'!$A$2:$E$70,5,FALSE) -> Trsf | S151: Trsf 20/04/21
A152: 44196 | B152: =MONTH(A152) -> 12 | C152: =YEAR(A152) -> 2020 | D152: INV2020/00000068 | E152: =VLOOKUP(F152,'Set up'!$A$2:$C$70,2,FALSE) -> C00000010 | F152: Yew Seng Gardening Supply Sdn Bhd | G152: RA CSM 450 30kg 79m(L) X 1040mm(W) | H152: 8 | I152: =VLOOKUP(F152,'Set up'!$A$2:$C$70,3,FALSE) -> 120 | J152: =VLOOKUP(F152,'Set up'!$A$2:$D$70,4,FALSE) -> 120 | K152: =A152+J152 -> 44316 | L152: =MONTH(K152) -> 4 | M152: =YEAR(K152) -> 2021 | N152: 1680 | O152: =SUM(-N152) -> -1680 | P152: =SUM(N152+O152) -> 0 | Q152: =SUM(Q151+N152) -> 203395.5 | R152: =VLOOKUP(F152,'Set up'!$A$2:$E$70,5,FALSE) -> Trsf | S152: Trsf 20/04/21
A153: 44196 | B153: =MONTH(A153) -> 12 | C153: =YEAR(A153) -> 2020 | D153: INV2020/00000068 | E153: =VLOOKUP(F153,'Set up'!$A$2:$C$70,2,FALSE) -> C00000010 | F153: Yew Seng Gardening Supply Sdn Bhd | G153: RA Talcum Powder (25kg) | H153: 10 | I153: =VLOOKUP(F153,'Set up'!$A$2:$C$70,3,FALSE) -> 120 | J153: =VLOOKUP(F153,'Set up'!$A$2:$D$70,4,FALSE) -> 120 | K153: =A153+J153 -> 44316 | L153: =MONTH(K153) -> 4 | M153: =YEAR(K153) -> 2021 | N153: 550 | O153: =SUM(-N153) -> -550 | P153: =SUM(N153+O153) -> 0 | Q153: =SUM(Q152+N153) -> 203945.5 | R153: =VLOOKUP(F153,'Set up'!$A$2:$E$70,5,FALSE) -> Trsf | S153: Trsf 20/04/21
A154: 44196 | B154: =MONTH(A154) -> 12 | C154: =YEAR(A154) -> 2020 | D154: INV2020/00000068 | E154: =VLOOKUP(F154,'Set up'!$A$2:$C$70,2,FALSE) -> C00000010 | F154: Yew Seng Gardening Supply Sdn Bhd | G154: RA Butanox M50 (5kg) | H154: 2 | I154: =VLOOKUP(F154,'Set up'!$A$2:$C$70,3,FALSE) -> 120 | J154: =VLOOKUP(F154,'Set up'!$A$2:$D$70,4,FALSE) -> 120 | K154: =A154+J154 -> 44316 | L154: =MONTH(K154) -> 4 | M154: =YEAR(K154) -> 2021 | N154: 190 | O154: =SUM(-N154) -> -190 | P154: =SUM(N154+O154) -> 0 | Q154: =SUM(Q153+N154) -> 204135.5 | R154: =VLOOKUP(F154,'Set up'!$A$2:$E$70,5,FALSE) -> Trsf | S154: Trsf 20/04/21
A155: 44200 | B155: =MONTH(A155) -> 1 | C155: =YEAR(A155) -> 2021 | D155: INV2020/00000069 | E155: =VLOOKUP(F155,'Set up'!$A$2:$C$70,2,FALSE) -> C00000013a | F155: Cash - PMC Sdn Bhd | G155: RA Tooling Gelcoat RP92 (22Kg) | H155: 2 | I155: =VLOOKUP(F155,'Set up'!$A$2:$C$70,3,FALSE) -> Cash | J155: =VLOOKUP(F155,'Set up'!$A$2:$D$70,4,FALSE) -> 0 | K155: =A155+J155 -> 44200 | L155: =MONTH(K155) -> 1 | M155: =YEAR(K155) -> 2021 | N155: 1540 | O155: =-N155 -> -1540 | P155: =SUM(N155+O155) -> 0 | Q155: =SUM(Q154+N155) -> 205675.5 | R155: =VLOOKUP(F155,'Set up'!$A$2:$E$70,5,FALSE) -> Chq | S155: Bank in 2-5/1/2021
A156: 44200 | B156: =MONTH(A156) -> 1 | C156: =YEAR(A156) -> 2021 | D156: INV2020/00000069 | E156: =VLOOKUP(F156,'Set up'!$A$2:$C$70,2,FALSE) -> C00000013a | F156: Cash - PMC Sdn Bhd | G156: RA CSM 450 54kg 64m(L) X 1860mm(W) | H156: 2 | I156: =VLOOKUP(F156,'Set up'!$A$2:$C$70,3,FALSE) -> Cash | J156: =VLOOKUP(F156,'Set up'!$A$2:$D$70,4,FALSE) -> 0 | K156: =A156+J156 -> 44200 | L156: =MONTH(K156) -> 1 | M156: =YEAR(K156) -> 2021 | N156: 810 | O156: =-N156 -> -810 | P156: =SUM(N156+O156) -> 0 | Q156: =SUM(Q155+N156) -> 206485.5 | R156: =VLOOKUP(F156,'Set up'!$A$2:$E$70,5,FALSE) -> Chq | S156: Bank in 2-5/1/2021
...

Sheet Set up
A1: Customer Name | B1: Customer Code | C1: Payment Term | D1: Term | E1: Payment mode
A2: Kelnico Marketing | B2: C00000001 | C2: Cash | D2: 0 | E2: Trsf
A3: Sley | B3: C00000002 | C3: Cash | D3: 0 | E3: Chq
A4: Pandian Art Gallery Manufacturing | B4: C00000003 | C4: 45 | D4: 45 | E4: PD Chq
A5: Siew Min Lorry Sdn Bhd | B5: C00000004 | C5: 120 | D5: 120 | E5: Chq
A6: Artscene Creative | B6: C00000005 | C6: Cash | D6: 0 | E6: Chq
A7: Perniagaan Fibra Sahih | B7: C00000006 | C7: Cash | D7: 0 | E7: Chq
A8: Chin Fibreglass (M) Sdn Bhd | B8: C00000007 | C8: Cash | D8: 0 | E8: Trsf
A9: Wonderland Design Productions Studio | B9: C00000008 | C9: Cash | D9: 0 | E9: Trsf
A10: JMC Steel Engineering Sdn Bhd | B10: C00000009 | C10: 60 | D10: 60 | E10: Chq
A11: Yew Seng Gardening Supply Sdn Bhd | B11: C00000010 | C11: 120 | D11: 120 | E11: Trsf
A12: JT Johan Sdn Bhd | B12: C00000011 | C12: Cash | D12: 0 | E12: Trsf
A13: Cash - Hamdan | B13: C00000012 | C13: Cash | D13: 0 | E13: Cash
A14: Cash - PMC Sdn Bhd | B14: C00000013a | C14: Cash | D14: 0 | E14: Chq
A15: Protech Master Coach Sdn Bhd | B15: C00000013 | C15: Cash | D15: 0 | E15: Chq
A16: IK Fibre Glass Enterprise | B16: C00000014 | C16: Cash | D16: 0 | E16: Cash
A17: S&J Business Solutions | B17: C00000015 | C17: Cash | D17: 0 | E17: Trsf
A18: Win Fiber Sdn Bhd | B18: C00000016 | C18: Cash | D18: 0 | E18: Trsf
A19: Aumada Energy & Technologies (M) Sdn Bhd | B19: C00000017 | C19: Cash | D19: 0 | E19: Trsf
A20: Living Divani (M) Sdn Bhd | B20: C00000018 | C20: Cash | D20: 0 | E20: Trsf
A21: Desuki Affela Empire Enterprise | B21: C00000019 | C21: Cash | D21: 0 | E21: Trsf
A22: WSK Tanks Sdn Bhd | B22: C00000020 | C22: Cash | D22: 0 | E22: Trsf
A23: KT Profesional Fiber | B23: C00000021 | C23: Cash | D23: 0 | E23: PD Chq
... A39: Choi Fook Sing Enterprise Sdn Bhd | B39: C00000036 | C39: Cash | D39: 0 | E39: Trsf
A40: Suntruck Sdn Bhd | B40: C00000037 | C40: 30 | D40: 30 | E40: Chq
A41: WSA Engineering Sdn Bhd | B41: C00000038 | C41: Cash | D41: 0 | E41: Trsf
A42: Bestway Bina Sdn Bhd | B42: C00000039 | C42: Cash | D42: 0 | E42: Trsf
A43: Dynamic Builders Trading | B43: C00000040 | C43: Cash | D43: 0 | E43: Cash
A44: Airebus Sdn Bhd | B44: C00000041 | C44: Cash | D44: 0 | E44: Trsf
A45: Welltech (M) Sdn Bhd | B45: C00000042 | C45: Cash | D45: 0 | E45: Trsf
A46: RBD World Wide Sdn Bhd | B46: C00000043 | C46: Cash | D46: 0 | E46: Trsf
A47: Cash - Encik Razzak | B47: C00000044 | C47: Cash | D47: 0 | E47: Cash
A48: Kelnico Sdn Bhd | B48: C00000045 | C48: Cash | D48: 0 | E48: Trsf
A49: Berkat Fibreglass | B49: C00000046 | C49: Cash | D49: 0 | E49: Cash
A50: KAD Builders Sdn Bhd | B50: C00000047 | C50: Cash | D50: 0 | E50: Cash
A51: Cash - Encik Mohammad Mongal | B51: C00000048 | C51: Cash | D51: 0 | E51: Cash
A52: DOB Engineering Solutions | B52: C00000049 | C52: Cash | D52: 0 | E52: Cash
... A67: Cash - Encik Alang | B67: C00000064 | C67: Cash | D67: 0 | E67: Cash

Sheet Customer Payment Term
A1: Customer Payment Term | V1: Customer Payment Term
A4: Sum of Sales Amount | C4: Term | V4: Sum of Sales Amount | W4: Year (Sales) | X4: Term
A5: Year (Sales) | B5: Customer Name | C5: 0 | D5: 45 | E5: 60 | F5: 120 | G5: #N/A | H5: 30 | I5: Grand Total | W5: 2019 | X5: 2019 Total | Y5: 2020 | AD5: 2020 Total | AE5: 2021 | AJ5: 2021 Total | AK5: 2022 | AP5: 2022 Total | AQ5: Grand Total
A6: 2019 | B6: Kelnico Marketing | C6: 2973 | I6: 2973 | V6: Customer Name | W6: 0 | Y6: 0 | Z6: 45 | AA6: 60 | AB6: 120 | AC6: #N/A | AE6: 0 | AF6: 45 | AG6: 60 | AH6: 120 | AI6: #N/A | AK6: 0 | AL6: 45 | AM6: 60 | AN6: 120 | AO6: #N/A
A7: 2019 Total | C7: 2973 | I7: 2973 | V7: Artscene Creative | Y7: 9334 | AD7: 9334 | AE7: 13661.4 | AJ7: 13661.4 | AQ7: 22995.4
A8: 2020 | B8: Artscene Creative | C8: 9334 | I8: 9334 | V8: Chin Fibreglass (M) Sdn Bhd | Y8: 5606 | AD8: 5606 | AQ8: 5606
B9: Chin Fibreglass (M) Sdn Bhd | C9: 5606 | I9: 5606 | V9: JMC Steel Engineering Sdn Bhd | AA9: 4191.2 | AD9: 4191.2 | AG9: 23646.6 | AJ9: 23646.6 | AM9: 37167.5 | AP9: 37167.5 | AQ9: 65005.3
B10: JMC Steel Engineering Sdn Bhd | E10: 4191.2 | I10: 4191.2 | V10: Kelnico Marketing | W10: 2973 | X10: 2973 | Y10: 34235 | AD10: 34235 | AE10: 22043 | AJ10: 22043 | AK10: 23044 | AP10: 23044 | AQ10: 82295
B11: Kelnico Marketing | C11: 34235 | I11: 34235 | V11: Pandian Art Gallery Manufacturing | Z11: 28025.7 | AD11: 28025.7 | AF11: 34482.5 | AJ11: 34482.5 | AL11: 43991 | AP11: 43991 | AQ11: 106499.2
B12: Pandian Art Gallery Manufacturing | D12: 28025.7 | I12: 28025.7 | V12: Perniagaan Fibra Sahih | Y12: 4008 | AD12: 4008 | AE12: 240 | AJ12: 240 | AK12: 11828.5 | AP12: 11828.5 | AQ12: 16076.5
B13: Perniagaan Fibra Sahih | C13: 4008 | I13: 4008 | V13: Siew Min Lorry Sdn Bhd | AB13: 52285.6 | AD13: 52285.6 | AH13: 85763 | AJ13: 85763 | AN13: 101459.4 | AP13: 101459.4 | AQ13: 239508
B14: Siew Min Lorry Sdn Bhd | F14: 52285.6 | I14: 52285.6 | V14: Sley | Y14: 2067 | AD14: 2067 | AE14: 3432 | AJ14: 3432 | AQ14: 5499
B15: Sley | C15: 2067 | I15: 2067 | V15: Wonderland Design Productions Studio | Y15: 9082 | AD15: 9082 | AE15: 8568 | AJ15: 8568 | AQ15: 17650
B16: Wonderland Design Productions Studio | C16: 9082 | I16: 9082 | V16: Yew Seng Gardening Supply Sdn Bhd | AB16: 50446 | AD16: 50446 | AH16: 140677.6 | AJ16: 140677.6 | AN16: 206833.5 | AP16: 206833.5 | AQ16: 397957.1
B17: Yew Seng Gardening Supply Sdn Bhd | F17: 50446 | I17: 50446 | V17: JT Johan Sdn Bhd | Y17: 1082.8 | AD17: 1082.8 | AQ17: 1082.8
B18: JT Johan Sdn Bhd | C18: 1082.8 | I18: 1082.8 | V18: Cash - Muhammad Syahin Bin | AC18: 799.2 | AD18: 799.2 | AQ18: 799.2
B19: Cash - Muhammad Syahin Bin | G19: 799.2 | I19: 799.2 | V19: Cash - PMC | AI19: 3070 | AJ19: 3070 | AQ19: 3070
A20: 2020 Total | C20: 65414.8 | D20: 28025.7 | E20: 4191.2 | F20: 102731.6 | G20: 799.2 | I20: 201162.5 | V20: IK Fibre Glass Enterprise | AE20: 8402 | AJ20: 8402 | AQ20: 8402
A21: 2021 | B21: Artscene Creative | C21: 13661.4 | I21: 13661.4 | V21: S&J Business Solutions | AE21: 4247 | AJ21: 4247 | AQ21: 4247
B22: JMC Steel Engineering Sdn Bhd | E22: 23646.6 | I22: 23646.6 | V22: Win Fiber Sdn Bhd | AE22: 10807.25 | AJ22: 10807.25 | AQ22: 10807.25
B23: Kelnico Marketing | C23: 22043 | I23: 22043 | V23: Living Divani (M) Sdn Bhd | AE23: 9592 | AJ23: 9592 | AQ23: 9592
B24: Pandian Art Gallery Manufacturing | D24: 34482.5 | I24: 34482.5 | V24: Desuki Affela Empire Enterprise | AE24: 31182 | AJ24: 31182 | AK24: 76338.9 | AP24: 76338.9 | AQ24: 107520.9
B25: Perniagaan Fibra Sahih | C25: 240 | I25: 240 | V25: WSK Tanks Sdn Bhd | AE25: 204219.6 | AJ25: 204219.6 | AK25: 583746.3 | AP25: 583746.3 | AQ25: 787965.9
B26: Siew Min Lorry Sdn Bhd | F26: 85763 | I26: 85763 | V26: Cash - En Mat | AI26: 240 | AJ26: 240 | AQ26: 240
B27: Sley | C27: 3432 | I27: 3432 | V27: KT Profesional Fiber | AE27: 2024 | AJ27: 2024 | AK27: 79757.3 | AP27: 79757.3 | AQ27: 81781.3
B28: Wonderland Design Productions Studio | C28: 8568 | I28: 8568 | V28: SF Engineering Solution | AK28: 23064.7 | AP28: 23064.7 | AQ28: 23064.7
B29: Yew Seng Gardening Supply Sdn Bhd | F29: 140677.6 | I29: 140677.6 | V29: Bestway Engineering Solutions | AK29: 26300.5 | AP29: 26300.5 | AQ29: 26300.5
B30: Cash - PMC | G30: 3070 | I30: 3070 | V30: Worldwide Competence Sdn Bhd | AK30: 15169 | AP30: 15169 | AQ30: 15169
B31: IK Fibre Glass Enterprise | C31: 8402 | I31: 8402 | V31: LLL Automotive Sdn Bhd | AK31: 1238 | AP31: 1238 | AQ31: 1238
B32: S&J Business Solutions | C32: 4247 | I32: 4247 | V32: Megapower Service | AK32: 6907.6 | AP32: 6907.6 | AQ32: 6907.6
B33: Win Fiber Sdn Bhd | C33: 10807.25 | I33: 10807.25 | V33: Transform Star Sdn Bhd | AK33: 58888.8 | AP33: 58888.8 | AQ33: 58888.8
B34: Living Divani (M) Sdn Bhd | C34: 9592 | I34: 9592 | V34: CANCELLED INVOICE | AO34: 0 | AP34: 0 | AQ34: 0
B35: Desuki Affela Empire Enterprise | C35: 31182 | I35: 31182 | V35: Cash - Vinz Yew Kok Wah | AK35: 4447.5 | AP35: 4447.5 | AQ35: 4447.5
B36: WSK Tanks Sdn Bhd | C36: 204219.6 | I36: 204219.6 | V36: Cash - Big Jackfruit Trading | AK36: 1672.6 | AP36: 1672.6 | AQ36: 1672.6
B37: Cash - En Mat | G37: 240 | I37: 240 | V37: Hai Kee Hung Sdn Bhd | AK37: 4373 | AP37: 4373 | AQ37: 4373
B38: KT Profesional Fiber | C38: 2024 | I38: 2024 | V38: Cash - PMC Sdn Bhd | AE38: 26393.4 | AJ38: 26393.4 | AQ38: 26393.4
B39: Cash - PMC Sdn Bhd | C39: 26393.4 | I39: 26393.4 | V39: Aumada Energy & Technologies (M) Sdn Bhd | AE39: 855 | AJ39: 855 | AQ39: 855
B40: Aumada Energy & Technologies (M) Sdn Bhd | C40: 855 | I40: 855 | V40: Grand Total | W40: 2973 | X40: 2973 | Y40: 65414.8 | Z40: 28025.7 | AA40: 4191.2 | AB40: 102731.6 | AC40: 799.2 | AD40: 201162.5 | AE40: 345666.65 | AF40: 34482.5 | AG40: 23646.6 | AH40: 226440.6 | AI40: 3310 | AJ40: 633546.35 | AK40: 916776.7 | AL40: 43991 | AM40: 37167.5 | AN40: 308292.9 | AO40: 0 | AP40: 1306228.1 | AQ40: 2143910
A41: 2021 Total | C41: 345666.65 | D41: 34482.5 | E41: 23646.6 | F41: 226440.6 | G41: 3310 | I41: 633546.35
A42: 2022 | B42: JMC Steel Engineering Sdn Bhd | E42: 41800.3 | I42: 41800.3
B43: Kelnico Marketing | C43: 26376 | I43: 26376
B44: Pandian Art Gallery Manufacturing | D44: 51210 | I44: 51210
B45: Perniagaan Fibra Sahih | C45: 11828.5 | I45: 11828.5
B46: Siew Min Lorry Sdn Bhd | F46: 101459.4 | I46: 101459.4
B47: Yew Seng Gardening Supply Sdn Bhd | F47: 232471 | I47: 232471
B48: Desuki Affela Empire Enterprise | C48: 82475 | I48: 82475
B49: WSK Tanks Sdn Bhd | C49: 719068.9 | I49: 719068.9
B50: KT Profesional Fiber | C50: 88508.3 | I50: 88508.3
B51: SF Engineering Solution | C51: 26086.7 | I51: 26086.7
B52: Bestway Engineering Solutions | C52: 26300.5 | I52: 26300.5
B53: LLL Automotive Sdn Bhd | C53: 1238 | I53: 1238
B54: Worldwide Competence Sdn Bhd | C54: 15169 | I54: 15169
B55: Megapower Service | C55: 8970.6 | I55: 8970.6
B56: Transform Star Sdn Bhd | C56: 58888.8 | I56: 58888.8
B57: Cash - Vinz Yew Kok Wah | C57: 4447.5 | I57: 4447.5
B58: CANCELLED INVOICE | G58: 0 | I58: 0
B59: Cash - Big Jackfruit Trading | C59: 1732.6 | I59: 1732.6
B60: Hai Kee Hung Sdn Bhd | C60: 4373 | I60: 4373
B61: Cash - Zaina | C61: 260 | I61: 260
B62: Cash - Zaidi | C62: 375 | I62: 375
A63: 2022 Total | C63: 1076098.4 | D63: 51210 | E63: 41800.3 | F63: 333930.4 | G63: 0 | I63: 1503039.1
A64: 2023 | B64: JMC Steel Engineering Sdn Bhd | E64: 36638.2 | I64: 36638.2
B65: Kelnico Marketing | C65: 11804 | I65: 11804
B66: Pandian Art Gallery Manufacturing | D66: 10972 | I66: 10972
B67: Perniagaan Fibra Sahih | C67: 14405.2 | I67: 14405.2
B68: Siew Min Lorry Sdn Bhd | F68: 1620 | I68: 1620
B69: Yew Seng Gardening Supply Sdn Bhd | F69: 183637.4 | I69: 183637.4
B70: IK Fibre Glass Enterprise | C70: 113330.1 | I70: 113330.1
B71: Desuki Affela Empire Enterprise | C71: 88097.9 | I71: 88097.9
B72: WSK Tanks Sdn Bhd | C72: 566294.1 | I72: 566294.1
B73: KT Profesional Fiber | C73: 80917.5 | I73: 80917.5
B74: SF Engineering Solution | C74: 33694.2 | I74: 33694.2
B75: Bestway Engineering Solutions | C75: 17384 | I75: 17384
B76: Megapower Service | C76: 3972.5 | I76: 3972.5
B77: Transform Star Sdn Bhd | C77: 27345.7 | I77: 27345.7
B78: Cash - Vinz Yew Kok Wah | C78: 250 | I78: 250
B79: CANCELLED INVOICE | G79: 0 | I79: 0
B80: Cash - ZTY Fibre | C80: 125347.1 | I80: 125347.1
B81: Cash - PMC Sdn Bhd | C81: 111066.9 | I81: 111066.9
B82: Cash - MLGaia Enterprise | C82: 1313 | I82: 1313
B83: Choi Fook Sing Enterprise Sdn Bhd | C83: 1791 | I83: 1791
B84: Suntruck Sdn Bhd | H84: 115065.7 | I84: 115065.7
B85: WSA Engineering Sdn Bhd | C85: 3063 | I85: 3063
B86: Bestway Bina Sdn Bhd | C86: 5351 | I86: 5351
B87: Dynamic Builders Trading | C87: 48 | I87: 48
B88: Airebus Sdn Bhd | C88: 2363 | I88: 2363
B89: Welltech (M) Sdn Bhd | C89: 168528.7 | I89: 168528.7
B90: RBD World Wide Sdn Bhd | C90: 9653.8 | I90: 9653.8
B91: Cash - Hamdan | C91: 4709.2 | I91: 4709.2
B92: Cash - Encik Razzak | C92: 2131 | I92: 2131
A93: 2023 Total | C93: 1392860.9 | D93: 10972 | E93: 36638.2 | F93: 185257.4 | G93: 0 | H93: 115065.7 | I93: 1740794.2
A94: 2024 | B94: Artscene Creative | C94: 2439.6 | I94: 2439.6
B95: JMC Steel Engineering Sdn Bhd | E95: 38345.3 | I95: 38345.3
B96: Pandian Art Gallery Manufacturing | D96: 18380 | I96: 18380
B97: Perniagaan Fibra Sahih | C97: 27746.5 | I97: 27746.5
B98: Yew Seng Gardening Supply Sdn Bhd | F98: 300024.3 | I98: 300024.3
B99: IK Fibre Glass Enterprise | C99: 16316 | I99: 16316
B100: Desuki Affela Empire Enterprise | C100: 81301.1 | I100: 81301.1
B101: KT Profesional Fiber | C101: 26160.6 | I101: 26160.6
B102: Megapower Service | C102: 12534.4 | I102: 12534.4
...

Sheet Transport_by month (estimate)
A3: Period (Sales) | B3: Date | C3: Invoice No | D3: Customer Name | E3: Amount
A4: 12 | B4: 43822 | C4: INV2019/00000001 | D4: Kelnico Marketing | E4: 80
A5: 12 Total | E5: =SUM(E4) -> 80
A6: 6 | B6: 43984 | C6: INV2020/00000002 | D6: Kelnico Marketing | E6: 80
B7: 43993 | C7: INV2020/00000003 | D7: Sley | E7: 80
B8: 43999 | C8: INV2020/00000004 | D8: Kelnico Marketing | E8: 80
B9: 44004 | C9: INV2020/00000005 | D9: Pandian Art Gallery Manufacturing | E9: 80
A10: 6 Total | E10: =SUM(E6:E9) -> 320
A11: Total | E11: =SUM(E10,E5) -> 400
A14: Period (Sales) | B14: Date | C14: Invoice No | D14: Customer Name | E14: Amount
A15: 7 | B15: 44013 | C15: INV2020/00000006 | D15: Siew Min Lorry Sdn Bhd | E15: 80
B16: 44026 | C16: INV2020/00000007 | D16: Pandian Art Gallery Manufacturing | E16: 80
B17: 44027 | C17: INV2020/00000008 | D17: Kelnico Marketing | E17: 80
A18: 7 Total | E18: =SUM(E15:E17) -> 240
A19: 8 | B19: 44044 | C19: INV2020/00000009 | D19: Siew Min Lorry Sdn Bhd | E19: 80
B20: 44051 | C20: INV2020/00000010 | D20: Siew Min Lorry Sdn Bhd | E20: 80
C21: INV2020/00000011 | D21: Siew Min Lorry Sdn Bhd | E21: 80
B22: 44053 | C22: INV2020/00000012 | D22: Artscene Creative | E22: 80
C23: INV2020/00000013 | D23: Pandian Art Gallery Manufacturing | E23: 80
B24: 44055 | C24: INV2020/00000014 | D24: Kelnico Marketing | E24: 80
B25: 44056 | C25: INV2020/00000015 | D25: Kelnico Marketing | E25: 80
B26: 44062 | C26: INV2020/00000016 | D26: Pandian Art Gallery Manufacturing | E26: 80
C27: INV2020/00000017 | D27: Perniagaan Fibra Sahih | E27: 80
B28: 44065 | C28: INV2020/00000018 | D28: Chin Fibreglass (M) Sdn Bhd | E28: 80
C29: INV2020/00000019 | D29: Wonderland Design Productions Studio | E29: 80
B30: 44067 | C30: INV2020/00000020 | D30: Pandian Art Gallery Manufacturing | E30: 80
B31: 44068 | C31: INV2020/00000021 | D31: JMC Steel Engineering Sdn Bhd | E31: 80
C32: INV2020/00000022 | D32: Kelnico Marketing | E32: 80
B33: 44070 | C33: INV2020/00000023 | D33: Yew Seng Gardening Supply Sdn Bhd | E33: 80
A34: 8 Total | E34: =SUM(E19:E33) -> 1200
A35: 9 | B35: 44075 | C35: INV2020/00000024 | D35: Wonderland Design Productions Studio | E35: 80
B36: 44076 | C36: INV2020/00000025 | D36: Kelnico Marketing | E36: 80
B37: 44079 | C37: INV2020/00000026 | D37: Kelnico Marketing | E37: 80
B38: 44091 | C38: INV2020/00000027 | D38: Siew Min Lorry Sdn Bhd | E38: 80
C39: INV2020/00000028 | D39: Kelnico Marketing | E39: 80
B40: 44096 | C40: INV2020/00000029 | D40: Siew Min Lorry Sdn Bhd | E40: 80
B41: 44097 | C41: INV2020/00000030 | D41: Yew Seng Gardening Supply Sdn Bhd | E41: 80
C42: INV2020/00000031 | D42: Kelnico Marketing | E42: 80
B43: 44100 | C43: INV2020/00000032 | D43: Kelnico Marketing | E43: 80
A44: 9 Total | E44: =SUM(E35:E43) -> 720
A45: Total | E45: =SUM(E44,E34,E18) -> 2160
A48: Period (Sales) | B48: Date | C48: Invoice No | D48: Customer Name | E48: Amount
A49: 10 | B49: 44109 | C49: INV2020/00000033 | D49: Artscene Creative | E49: 80
C50: INV2020/00000034 | D50: Pandian Art Gallery Manufacturing | E50: 80
B51: 44112 | C51: INV2020/00000035 | D51: Siew Min Lorry Sdn Bhd | E51: 80
B52: 44116 | C52: INV2020/00000036 | D52: Siew Min Lorry Sdn Bhd | E52: 80
C53: INV2020/00000037 | D53: Kelnico Marketing | E53: 80
B54: 44123 | C54: INV2020/00000038 | D54: Chin Fibreglass (M) Sdn Bhd | E54: 80
B55: 44121 | C55: INV2020/00000039 | D55: Pandian Art Gallery Manufacturing | E55: 80
C56: INV2020/00000040 | D56: Pandian Art Gallery Manufacturing | E56: 80
C57: INV2020/00000041 | D57: Kelnico Marketing | E57: 80
C58: INV2020/00000042 | D58: Artscene Creative | E58: 80
B59: 44125 | C59: INV2020/00000043 | D59: Artscene Creative | E59: 80
C60: INV2020/00000044 | D60: Yew Seng Gardening Supply Sdn Bhd | E60: 80
B61: 44130 | C61: INV2020/00000045 | D61: Pandian Art Gallery Manufacturing | E61: 80
B62: 44135 | C62: INV2020/00000046 | D62: Kelnico Marketing | E62: 80
C63: INV2020/00000047 | D63: Artscene Creative | E63: 80
A64: 10 Total | E64: =SUM(E49:E63) -> 1200
A65: 11 | B65: 44144 | C65: INV2020/00000048 | D65: Perniagaan Fibra Sahih | E65: 80
B66: 44145 | C66: INV2020/00000049 | D66: Kelnico Marketing | E66: 80
C67: INV2020/00000050 | D67: Artscene Creative | E67: 80
B68: 44146 | C68: INV2020/00000051 | D68: JMC Steel Engineering Sdn Bhd | E68: 80
B69: 44153 | C69: INV2020/00000052 | D69: Kelnico Marketing | E69: 80
B70: 44159 | C70: INV2020/00000053 | D70: Kelnico Marketing | E70: 80
B71: 44155 | C71: INV2020/00000054 | D71: Yew Seng Gardening Supply Sdn Bhd | E71: 80
B72: 44156 | C72: INV2020/00000055 | D72: Wonderland Design Productions Studio | E72: 80
B73: 44158 | C73: INV2020/00000056 | D73: Artscene Creative | E73: 80
B74: 44159 | C74: INV2020/00000057 | D74: JT Johan Sdn Bhd | E74: 80
C75: INV2020/00000058 | D75: Pandian Art Gallery Manufacturing | E75: 80
B76: 44162 | C76: INV2020/00000059 | D76: Kelnico Marketing | E76: 80
B77: 44163 | C77: INV2020/00000060 | D77: JMC Steel Engineering Sdn Bhd | E77: 80
B78: 44165 | C78: INV2020/00000061 | D78: Wonderland Design Productions Studio | E78: 80
C79: INV2020/00000062&3 | D79: Yew Seng Gardening Supply Sdn Bhd | E79: 80
A80: 11 Total | E80: =SUM(E65:E79) -> 1200
A81: 12 | B81: 44170 | C81: INV2020/00000064 | D81: Cash - Muhammad Syahin Bin | E81: 80
B82: 44180 | C82: INV2020/00000065 | D82: Kelnico Marketing | E82: 80
B83: 44191 | C83: INV2020/00000066 | D83: Siew Min Lorry Sdn Bhd | E83: 80
B84: 44195 | C84: INV2020/00000067 | D84: Pandian Art Gallery Manufacturing | E84: 80
B85: 44196 | C85: INV2020/00000068 | D85: Yew Seng Gardening Supply Sdn Bhd | E85: 80
A86: 12 Total | E86: =SUM(E81:E85) -> 400
A87: Total | E87: =SUM(E86,E80,E64) -> 2800
A90: Period (Sales) | B90: Date | C90: Invoice No | D90: Customer Name | E90: Amount
A91: 1 | B91: 44200 | C91: INV2020/00000069 | D91: Cash - PMC | E91: 80
B92: 44207 | C92: INV2020/00000070 | D92: Yew Seng Gardening Supply Sdn Bhd | E92: 80
B93: 44204 | C93: INV2020/00000071 | D93: Cash - PMC | E93: 80
B94: 44205 | C94: INV2020/00000072 | D94: Pandian Art Gallery Manufacturing | E94: 80
B95: 44214 | C95: INV2020/00000073 | D95: Cash - PMC | E95: 80
B96: 44223 | C96: INV2020/00000074 | D96: Pandian Art Gallery Manufacturing | E96: 80
B97: 44225 | C97: INV2020/00000075 | D97: Kelnico Marketing | E97: 80
C98: INV2020/00000076 | D98: Yew Seng Gardening Supply Sdn Bhd | E98: 80
A99: 1 Total | E99: =SUM(E91:E98) -> 640
A100: 2 | B100: 44230 | C100: INV2020/00000077 | D100: IK Fibre Glass Enterprise | E100: 80
B101: 44229 | C101: INV2020/00000078 | D101: Artscene Creative | E101: 80
B102: 44233 | C102: INV2020/00000079 | D102: IK Fibre Glass Enterprise | E102: 80
B103: 44236 | C103: INV2020/00000080 | D103: Cash - PMC | E103: 80
B104: 44244 | C104: INV2020/00000081 | D104: Artscene Creative | E104: 80
B105: 44246 | C105: INV2020/00000082 | D105: Kelnico Marketing | E105: 80
B106: 44249 | C106: INV2020/00000083 | D106: Siew Min Lorry Sdn Bhd | E106: 80
B107: 44250 | C107: INV2020/00000084 | D107: Wonderland Design Productions Studio | E107: 80
B108: 44253 | C108: INV2020/00000085 | D108: S&J Business Solutions | E108: 80
...

Sheet Inv No with date
A1: Year (Sales) | B1: 2022
A3: Sum of Sales Amount
A4: Period (Sales) | B4: Invoice Date | C4: Invoice No | D4: Customer Name | E4: Total
A5: 3 | B5: 44625 | C5: INV00000209 | D5: KT Profesional Fiber | E5: 6301
B6: 44628 | C6: INV00000210 | D6: SF Engineering Solution | E6: 4873
C7: INV00000211 | D7: Yew Seng Gardening Supply Sdn Bhd | E7: 15280
B8: 44629 | C8: INV00000212 | D8: SF Engineering Solution | E8: 65
B9: 44631 | C9: INV00000213 | D9: Desuki Affela Empire Enterprise | E9: 6379.9
B10: 44632 | C10: INV00000214 | D10: SF Engineering Solution | E10: 390
C11: INV00000215 | D11: Perniagaan Fibra Sahih | E11: 2068
B12: 44634 | C12: INV00000216 | D12: WSK Tanks Sdn Bhd | E12: 3029
B13: 44635 | C13: INV00000217 | D13: Yew Seng Gardening Supply Sdn Bhd | E13: 14185
C14: INV00000218 | D14: WSK Tanks Sdn Bhd | E14: 11425
B15: 44637 | C15: INV00000219 | D15: Desuki Affela Empire Enterprise | E15: 315
B16: 44638 | C16: INV00000220 | D16: WSK Tanks Sdn Bhd | E16: 9888
B17: 44639 | C17: INV00000221 | D17: KT Profesional Fiber | E17: 8127.5
B18: 44641 | C18: INV00000222 | D18: Perniagaan Fibra Sahih | E18: 337.5
B19: 44643 | C19: INV00000223 | D19: WSK Tanks Sdn Bhd | E19: 8819
B20: 44645 | C20: INV00000224 | D20: WSK Tanks Sdn Bhd | E20: 14422
B21: 44649 | C21: INV00000225 | D21: Kelnico Marketing | E21: 3232
C22: INV00000226 | D22: WSK Tanks Sdn Bhd | E22: 7593
B23: 44651 | C23: INV00000227 | D23: Bestway Engineering Solutions | E23: 3555
A24: 3 Total | E24: 120284.9
A25: 4 | B25: 26/4/2022 | C25: INV00000250 | D25: Bestway Engineering Solutions | E25: 3799
B26: 44652 | C26: INV00000228 | D26: KT Profesional Fiber | E26: 6083.5
C27: INV00000229 | D27: WSK Tanks Sdn Bhd | E27: 9157.5
C28: INV00000230 | D28: SF Engineering Solution | E28: 3480
B29: 44656 | C29: INV00000231 | D29: WSK Tanks Sdn Bhd | E29: 10497.5
B30: 44659 | C30: INV00000232 | D30: Desuki Affela Empire Enterprise | E30: 6361.1
C31: INV00000233 | D31: Pandian Art Gallery Manufacturing | E31: 7316
B32: 44660 | C32: INV00000234 | D32: JMC Steel Engineering Sdn Bhd | E32: 5043
C33: INV00000235 | D33: WSK Tanks Sdn Bhd | E33: 8569.5
C34: INV00000236 | D34: Worldwide Competence Sdn Bhd | E34: 3881.5
B35: 44663 | C35: INV00000237 | D35: SF Engineering Solution | E35: 590
B36: 44664 | C36: INV00000238 | D36: Worldwide Competence Sdn Bhd | E36: 588
C37: INV00000239 | D37: WSK Tanks Sdn Bhd | E37: 10975.5
B38: 44665 | C38: INV00000240 | D38: KT Profesional Fiber | E38: 5746
B39: 44666 | C39: INV00000241 | D39: Worldwide Competence Sdn Bhd | E39: 2175
B40: 44667 | C40: INV00000242 | D40: WSK Tanks Sdn Bhd | E40: 10103.5
C41: INV00000243 | D41: Bestway Engineering Solutions | E41: 14088.5
B42: 44670 | C42: INV00000244 | D42: WSK Tanks Sdn Bhd | E42: 3076
B43: 44671 | C43: INV00000245 | D43: LLL Automotive Sdn Bhd | E43: 1170
B44: 44672 | C44: INV00000246 | D44: Siew Min Lorry Sdn Bhd | E44: 15222
C45: INV00000247 | D45: LLL Automotive Sdn Bhd | E45: 68
C46: INV00000248 | D46: Kelnico Marketing | E46: 2068
B47: 44673 | C47: INV00000248 | D47: Kelnico Marketing | E47: 420
B48: 44674 | C48: INV00000249 | D48: WSK Tanks Sdn Bhd | E48: 11151
B49: 44678 | C49: INV00000251 | D49: Yew Seng Gardening Supply Sdn Bhd | E49: 11160
B50: 44679 | C50: INV00000252 | D50: KT Profesional Fiber | E50: 5458
C51: INV00000253 | D51: WSK Tanks Sdn Bhd | E51: 11858.5
C52: INV00000254 | D52: Desuki Affela Empire Enterprise | E52: 6096.1
B53: 44680 | C53: INV00000255 | D53: Bestway Engineering Solutions | E53: 1350
B54: 44681 | C54: INV00000256 | D54: WSK Tanks Sdn Bhd | E54: 15244
A55: 4 Total | E55: 192796.7
A56: 5 | B56: 11/5/2022 | C56: INV00000261 | D56: Perniagaan Fibra Sahih | E56: 2534
B57: 44687 | C57: INV00000257 | D57: WSK Tanks Sdn Bhd | E57: 11530
C58: INV00000258 | D58: Bestway Engineering Solutions | E58: 1350
B59: 44688 | C59: INV00000259 | D59: WSK Tanks Sdn Bhd | E59: 16245
B60: 44691 | C60: INV00000260 | D60: JMC Steel Engineering Sdn Bhd | E60: 5100
B61: 44693 | C61: INV00000262 | D61: SF Engineering Solution | E61: 4317.9
C62: INV00000263 | D62: Worldwide Competence Sdn Bhd | E62: 8524.5
B63: 44695 | C63: INV00000264 | D63: Perniagaan Fibra Sahih | E63: 100
C64: INV00000265 | D64: WSK Tanks Sdn Bhd | E64: 10369.5
B65: 44697 | C65: INV00000266 | D65: Pandian Art Gallery Manufacturing | E65: 7336
B66: 44699 | C66: INV00000267 | D66: WSK Tanks Sdn Bhd | E66: 8417
B67: 44700 | C67: INV00000268 | D67: KT Profesional Fiber | E67: 3484
B68: 44701 | C68: INV00000269 | D68: WSK Tanks Sdn Bhd | E68: 13110
B69: 44702 | C69: INV00000270 | D69: Megapower Service | E69: 1239.6
C70: INV00000271 | D70: WSK Tanks Sdn Bhd | E70: 13110
B71: 44704 | C71: INV00000272 | D71: Yew Seng Gardening Supply Sdn Bhd | E71: 14715
C72: INV00000273 | D72: WSK Tanks Sdn Bhd | E72: 6750
C73: INV00000274 | D73: Desuki Affela Empire Enterprise | E73: 6201.1
B74: 44705 | C74: INV00000275 | D74: Siew Min Lorry Sdn Bhd | E74: 10120
B75: 44706 | C75: INV00000276 | D75: WSK Tanks Sdn Bhd | E75: 14068
B76: 44709 | C76: INV00000277 | D76: KT Profesional Fiber | E76: 3241
A77: 5 Total | E77: 161862.6
A78: 6 | B78: 44714 | C78: INV00000278 | D78: WSK Tanks Sdn Bhd | E78: 12427
B79: 44715 | C79: INV00000279 | D79: SF Engineering Solution | E79: 2112
B80: 44716 | C80: INV00000280 | D80: WSK Tanks Sdn Bhd | E80: 9000
B81: 44719 | C81: INV00000281 | D81: Kelnico Marketing | E81: 2356
B82: 44721 | C82: INV00000282 | D82: Yew Seng Gardening Supply Sdn Bhd | E82: 12690
C83: INV00000283 | D83: SF Engineering Solution | E83: 2112
B84: 44722 | C84: INV00000284 | D84: KT Profesional Fiber | E84: 2746
B85: 44723 | C85: INV00000285 | D85: WSK Tanks Sdn Bhd | E85: 4950
B86: 44725 | C86: INV00000286 | D86: Bestway Engineering Solutions | E86: 2158
B87: 44726 | C87: INV00000287 | D87: JMC Steel Engineering Sdn Bhd | E87: 3960
C88: INV00000288 | D88: Kelnico Marketing | E88: 3232
B89: 44730 | C89: INV00000289 | D89: WSK Tanks Sdn Bhd | E89: 4431.5
B90: 44732 | C90: INV00000290 | D90: Perniagaan Fibra Sahih | E90: 2068
B91: 44736 | C91: INV00000291 | D91: KT Profesional Fiber | E91: 3374.5
C92: INV00000292 | D92: WSK Tanks Sdn Bhd | E92: 5889
B93: 44740 | C93: INV00000293 | D93: Desuki Affela Empire Enterprise | E93: 6223.6
B94: 44741 | C94: INV00000294 | D94: Yew Seng Gardening Supply Sdn Bhd | E94: 18515
A95: 6 Total | E95: 98244.6
A96: 7 | B96: 44743 | C96: INV00000295 | D96: JMC Steel Engineering Sdn Bhd | E96: 1539
B97: 44754 | C97: INV00000296 | D97: Desuki Affela Empire Enterprise | E97: 5183.6
B98: 44756 | C98: INV00000297 | D98: WSK Tanks Sdn Bhd | E98: 12855.5
C99: INV00000298 | D99: Transform Star Sdn Bhd | E99: 8568.2
B100: 44760 | C100: INV00000299 | D100: WSK Tanks Sdn Bhd | E100: 9153
B101: 44762 | C101: INV00000300 | D101: WSK Tanks Sdn Bhd | E101: 925.5
...

Sheet Sales_by Inv No & by customer
A1: Year (Sales) | B1: 2022
D3: Values | N3: Sum of Sales Amount | P3: Year (Sales) | Q3: Period (Sales)
A4: Period (Sales) | B4: Invoice No | C4: Customer Name | D4: Sum of Sales Amount2 | E4: Sum of Collection | F4: Sum of Outstanding | P4: 2019 | Q4: 2019 Total | R4: 2020 | Y4: 2020 Total | Z4: 2021 | AJ4: 2021 Total | AK4: 2022 | AW4: 2022 Total | AX4: 2023 | BJ4: 2023 Total | BK4: 2024 | BS4: 2024 Total | BT4: Grand Total
A5: 6 | B5: INV00000278 | C5: WSK Tanks Sdn Bhd | D5: 12427 | E5: -12427 | F5: 0 | N5: Customer Name | O5: Invoice No | P5: 12 | R5: 6 | S5: 7 | T5: 8 | U5: 9 | V5: 10 | W5: 11 | X5: 12 | Z5: 6 | AA5: 9 | AB5: 10 | AC5: 11 | AD5: 12 | AE5: 1 | AF5: 2 | AG5: 3 | AH5: 4 | AI5: 5 | AK5: 6 | AL5: 7 | AM5: 8 | AN5: 9 | AO5: 10 | AP5: 11 | AQ5: 12 | AR5: 1 | AS5: 2 | AT5: 3 | AU5: 4 | AV5: 5 | AX5: 6 | AY5: 7 | AZ5: 8 | BA5: 9 | BB5: 10 | BC5: 11 | BD5: 12 | BE5: 1 | BF5: 2 | BG5: 3 | BH5: 4 | BI5: 5 | BK5: 6 | BL5: 7 | BM5: 8 | BN5: 1 | BO5: 2 | BP5: 3 | BQ5: 4 | BR5: 5
B6: INV00000279 | C6: SF Engineering Solution | D6: 2112 | E6: -2112 | F6: 0 | N6: Artscene Creative | O6: INV2020/00000012 | T6: 1586 | Y6: 1586 | BT6: 1586
B7: INV00000280 | C7: WSK Tanks Sdn Bhd | D7: 9000 | E7: -9000 | F7: 0 | O7: INV2020/00000033 | V7: 1496 | Y7: 1496 | BT7: 1496
B8: INV00000281 | C8: Kelnico Marketing | D8: 2356 | E8: -2356 | F8: 0 | O8: INV2020/00000042 | V8: 90 | Y8: 90 | BT8: 90
B9: INV00000282 | C9: Yew Seng Gardening Supply Sdn Bhd | D9: 12690 | E9: -12690 | F9: 0 | O9: INV2020/00000043 | V9: 1496 | Y9: 1496 | BT9: 1496
B10: INV00000283 | C10: SF Engineering Solution | D10: 2112 | E10: -2112 | F10: 0 | O10: INV2020/00000047 | V10: 1496 | Y10: 1496 | BT10: 1496
B11: INV00000284 | C11: KT Profesional Fiber | D11: 2746 | E11: -2746 | F11: 0 | O11: INV2020/00000050 | W11: 1630 | Y11: 1630 | BT11: 1630
B12: INV00000285 | C12: WSK Tanks Sdn Bhd | D12: 4950 | E12: -4950 | F12: 0 | O12: INV2020/00000056 | W12: 1540 | Y12: 1540 | BT12: 1540
B13: INV00000286 | C13: Bestway Engineering Solutions | D13: 2158 | E13: -2158 | F13: 0 | O13: INV2020/00000078 | AF13: 1750 | AJ13: 1750 | BT13: 1750
B14: INV00000287 | C14: JMC Steel Engineering Sdn Bhd | D14: 3960 | E14: -3960 | F14: 0 | O14: INV2020/00000081 | AF14: 225 | AJ14: 225 | BT14: 225
B15: INV00000288 | C15: Kelnico Marketing | D15: 3232 | E15: -3232 | F15: 0 | O15: INV00000103 | AI15: 1876 | AJ15: 1876 | BT15: 1876
B16: INV00000289 | C16: WSK Tanks Sdn Bhd | D16: 4431.5 | E16: -4431.5 | F16: 0 | O16: INV00000105 | AI16: 1826 | AJ16: 1826 | BT16: 1826
B17: INV00000290 | C17: Perniagaan Fibra Sahih | D17: 2068 | E17: -2068 | F17: 0 | O17: INV00000107 | AI17: 100 | AJ17: 100 | BT17: 100
B18: INV00000291 | C18: KT Profesional Fiber | D18: 3374.5 | E18: -3374.5 | F18: 0 | O18: INV00000113 | AA18: 1826 | AJ18: 1826 | BT18: 1826
B19: INV00000292 | C19: WSK Tanks Sdn Bhd | D19: 5889 | E19: -5889 | F19: 0 | O19: INV00000114 | AA19: 1926 | AJ19: 1926 | BT19: 1926
B20: INV00000293 | C20: Desuki Affela Empire Enterprise | D20: 6223.6 | E20: -6223.6 | F20: 0 | O20: INV00000122 | AA20: 1826 | AJ20: 1826 | BT20: 1826
B21: INV00000294 | C21: Yew Seng Gardening Supply Sdn Bhd | D21: 18515 | E21: -18515 | F21: 0 | O21: INV00000137 | AB21: 1926 | AJ21: 1926 | BT21: 1926
A22: 6 Total | D22: 98244.6 | E22: -98244.6 | F22: 0 | O22: INV00000150 | AC22: 380.4 | AJ22: 380.4 | BT22: 380.4
A23: 7 | B23: INV00000295 | C23: JMC Steel Engineering Sdn Bhd | D23: 1539 | E23: -1539 | F23: 0 | N23: Artscene Creative Total | T23: 1586 | V23: 4578 | W23: 3170 | Y23: 9334 | AA23: 5578 | AB23: 1926 | AC23: 380.4 | AF23: 1975 | AI23: 3802 | AJ23: 13661.4 | BT23: 22995.4
B24: INV00000296 | C24: Desuki Affela Empire Enterprise | D24: 5183.6 | E24: -5183.6 | F24: 0 | N24: Chin Fibreglass (M) Sdn Bhd | O24: INV2020/00000018 | T24: 2956 | Y24: 2956 | BT24: 2956
B25: INV00000297 | C25: WSK Tanks Sdn Bhd | D25: 12855.5 | E25: -12855.5 | F25: 0 | O25: INV2020/00000038 | V25: 2650 | Y25: 2650 | BT25: 2650
B26: INV00000298 | C26: Transform Star Sdn Bhd | D26: 8568.2 | E26: -8568.2 | F26: 0 | N26: Chin Fibreglass (M) Sdn Bhd Total | T26: 2956 | V26: 2650 | Y26: 5606 | BT26: 5606
B27: INV00000299 | C27: WSK Tanks Sdn Bhd | D27: 9153 | E27: -9153 | F27: 0 | N27: JMC Steel Engineering Sdn Bhd | O27: INV2020/00000021 | T27: 2552 | Y27: 2552 | BT27: 2552
B28: INV00000300 | C28: WSK Tanks Sdn Bhd | D28: 925.5 | E28: -925.5 | F28: 0 | O28: INV2020/00000051 | W28: 1231.2 | Y28: 1231.2 | BT28: 1231.2
B29: INV00000301 | C29: WSK Tanks Sdn Bhd | D29: 6625 | E29: -6625 | F29: 0 | O29: INV2020/00000060 | W29: 408 | Y29: 408 | BT29: 408
B30: INV00000302 | C30: Kelnico Marketing | D30: 4092 | E30: -4092 | F30: 0 | O30: INV00000088 | AG30: 6459.6 | AJ30: 6459.6 | BT30: 6459.6
B31: INV00000303 | C31: Yew Seng Gardening Supply Sdn Bhd | D31: 13445 | E31: -13445 | F31: 0 | O31: INV00000091 | AG31: 90 | AJ31: 90 | BT31: 90
B32: INV00000304 | C32: KT Profesional Fiber | D32: 2180 | E32: -2180 | F32: 0 | O32: INV00000100 | AH32: 7482 | AJ32: 7482 | BT32: 7482
B33: INV00000305 | C33: JMC Steel Engineering Sdn Bhd | D33: 4596.5 | E33: -4596.5 | F33: 0 | O33: INV00000109 | Z33: 3825 | AJ33: 3825 | BT33: 3825
A34: 7 Total | D34: 69163.3 | E34: -69163.3 | F34: 0 | O34: INV00000110 | Z34: 690 | AJ34: 690 | BT34: 690
A35: 8 | B35: INV00000306 | C35: Transform Star Sdn Bhd | D35: 12643.2 | E35: -12643 | F35: 0.2 | O35: INV00000135 | AB35: 5100 | AJ35: 5100 | BT35: 5100
B36: INV00000307 | C36: WSK Tanks Sdn Bhd | D36: 5268.6 | E36: -5268.6 | F36: 0 | O36: INV00000201 | AS36: 5940 | AW36: 5940 | BT36: 5940
B37: INV00000308 | C37: Kelnico Marketing | D37: 864 | E37: -864 | F37: 0 | O37: INV00000234 | AU37: 5043 | AW37: 5043 | BT37: 5043
B38: INV00000309 | C38: Megapower Service | D38: 2068 | E38: -2068 | F38: 0 | O38: INV00000260 | AV38: 5100 | AW38: 5100 | BT38: 5100
B39: INV00000310 | C39: WSK Tanks Sdn Bhd | D39: 4312.5 | E39: -4312.5 | F39: 0 | O39: INV00000287 | AK39: 3960 | AW39: 3960 | BT39: 3960
B40: INV00000311 | C40: CANCELLED INVOICE | D40: 0 | F40: 0 | O40: INV00000295 | AL40: 1539 | AW40: 1539 | BT40: 1539
B41: INV00000312 | C41: Siew Min Lorry Sdn Bhd | D41: 16536.7 | E41: -16536.7 | F41: 0 | O41: INV00000305 | AL41: 4596.5 | AW41: 4596.5 | BT41: 4596.5
B42: INV00000313 | C42: Pandian Art Gallery Manufacturing | D42: 7521 | E42: -7521 | F42: 0 | O42: INV00000317 | AM42: 762 | AW42: 762 | BT42: 762
B43: INV00000314 | C43: KT Profesional Fiber | D43: 3459 | E43: -3459 | F43: 0 | O43: INV00000322 | AN43: 3784 | AW43: 3784 | BT43: 3784
B44: INV00000315 | C44: Transform Star Sdn Bhd | D44: 5840 | E44: -5840 | F44: 0 | O44: INV00000350 | AO44: 1960.2 | AW44: 1960.2 | BT44: 1960.2
B45: INV00000316 | C45: WSK Tanks Sdn Bhd | D45: 6838.5 | E45: -6838.5 | F45: 0 | O45: INV00000360 | AP45: 4482.8 | AW45: 4482.8 | BT45: 4482.8
B46: INV00000317 | C46: JMC Steel Engineering Sdn Bhd | D46: 762 | E46: -762 | F46: 0 | O46: INV00000381 | AQ46: 4632.8 | AW46: 4632.8 | BT46: 4632.8
B47: INV00000318 | C47: Yew Seng Gardening Supply Sdn Bhd | D47: 15671 | E47: -15671 | F47: 0 | O47: INV00000417 | BE47: 5616 | BJ47: 5616 | BT47: 5616
B48: INV00000319 | C48: Transform Star Sdn Bhd | D48: 6006 | E48: -6006 | F48: 0 | O48: INV00000463 | BG48: 4461.8 | BJ48: 4461.8 | BT48: 4461.8
B49: INV00000320 | C49: Desuki Affela Empire Enterprise | D49: 6136.8 | E49: -6136.8 | F49: 0 | O49: INV00000486 | BH49: 220 | BJ49: 220 | BT49: 220
A50: 8 Total | D50: 93927.3 | E50: -93927.1 | F50: 0.2 | O50: INV00000499 | BH50: 4878.4 | BJ50: 4878.4 | BT50: 4878.4
A51: 9 | B51: INV00000321 | C51: WSK Tanks Sdn Bhd | D51: 9343.9 | E51: -9343.9 | F51: 0 | O51: INV00000513 | BI51: 220 | BJ51: 220 | BT51: 220
B52: INV00000322 | C52: JMC Steel Engineering Sdn Bhd | D52: 3784 | E52: -3784 | F52: 0 | O52: INV00000531 | BI52: 4621.2 | BJ52: 4621.2 | BT52: 4621.2
B53: INV00000323 | C53: WSK Tanks Sdn Bhd | D53: 11453.6 | E53: -11453.6 | F53: 0 | O53: INV00000562 | AY53: 220 | BJ53: 220 | BT53: 220
B54: INV00000324 | C54: Cash - Vinz Yew Kok Wah | D54: 2452 | E54: -2452 | F54: 0 | O54: INV00000589 | AZ54: 3124 | BJ54: 3124 | BT54: 3124
B55: INV00000325 | C55: WSK Tanks Sdn Bhd | D55: 1914 | E55: -1914 | F55: 0 | O55: INV00000600 | AZ55: 220 | BJ55: 220 | BT55: 220
B56: INV00000326 | C56: KT Profesional Fiber | D56: 2251 | E56: -2251 | F56: 0 | O56: INV00000635 | BA56: 540 | BJ56: 540 | BT56: 540
B57: INV00000327 | C57: WSK Tanks Sdn Bhd | D57: 13163 | E57: -13163 | F57: 0 | O57: INV00000676 | BB57: 1628 | BJ57: 1628 | BT57: 1628
B58: INV00000328 | C58: WSK Tanks Sdn Bhd | D58: 11823 | E58: -11823 | F58: 0 | O58: INV00000681 | BB58: 4818 | BJ58: 4818 | BT58: 4818
B59: INV00000329 | C59: Kelnico Marketing | D59: 1840 | E59: -1840 | F59: 0 | O59: INV00000738 | BD59: 6070.8 | BJ59: 6070.8 | BT59: 6070.8
B60: INV00000330 | C60: KT Profesional Fiber | D60: 3655.7 | E60: -3655.7 | F60: 0 | O60: INV00000769 | BN60: 6290.8 | BS60: 6290.8 | BT60: 6290.8
B61: INV00000331 | C61: Desuki Affela Empire Enterprise | D61: 3546.1 | E61: -3546.1 | F61: 0 | O61: INV00000808 | BO61: 5884.4 | BS61: 5884.4 | BT61: 5884.4
B62: INV00000332 | C62: Yew Seng Gardening Supply Sdn Bhd | D62: 11757.5 | E62: -11757.5 | F62: 0 | O62: INV00000819 | BP62: 3212 | BS62: 3212 | BT62: 3212
B63: INV00000333 | C63: KT Profesional Fiber | D63: 3595.6 | E63: -3595.6 | F63: 0 | O63: INV00000843 | BQ63: 6619.3 | BS63: 6619.3 | BT63: 6619.3
B64: INV00000334 | C64: SF Engineering Solution | D64: 2968.8 | E64: -2968.8 | F64: 0 | O64: INV00000844 | BQ64: 260 | BS64: 260 | BT64: 260
B65: INV00000335 | C65: SF Engineering Solution | D65: 840 | E65: -840 | F65: 0 | O65: INV00000858 | BQ65: 5334 | BS65: 5334 | BT65: 5334
B66: INV00000336 | C66: Transform Star Sdn Bhd | D66: 11266.8 | E66: -11266.8 | F66: 0 | O66: INV00000901 | BK66: 5042 | BS66: 5042 | BT66: 5042
B67: INV00000337 | C67: Cash - Vinz Yew Kok Wah | D67: 1995.5 | E67: -1995.5 | F67: 0 | O67: INV00000918 | BL67: 818.8 | BS67: 818.8 | BT67: 818.8
A68: 9 Total | D68: 97650.5 | E68: -97650.5 | F68: 0 | O68: INV00000925 | BL68: 4884 | BS68: 4884 | BT68: 4884
A69: 10 | B69: INV00000338 | C69: Yew Seng Gardening Supply Sdn Bhd | D69: 13065 | E69: -13065 | F69: 0 | N69: JMC Steel Engineering Sdn Bhd Total | T69: 2552 | W69: 1639.2 | Y69: 4191.2 | Z69: 4515 | AB69: 5100 | AG69: 6549.6 | AH69: 7482 | AJ69: 23646.6 | AK69: 3960 | AL69: 6135.5 | AM69: 762 | AN69: 3784 | AO69: 1960.2 | AP69: 4482.8 | AQ69: 4632.8 | AS69: 5940 | AU69: 5043 | AV69: 5100 | AW69: 41800.3 | AY69: 220 | AZ69: 3344 | BA69: 540 | BB69: 6446 | BD69: 6070.8 | BE69: 5616 | BG69: 4461.8 | BH69: 5098.4 | BI69: 4841.2 | BJ69: 36638.2 | BK69: 5042 | BL69: 5702.8 | BN69: 6290.8 | BO69: 5884.4 | BP69: 3212 | BQ69: 12213.3 | BS69: 38345.3 | BT69: 144621.6
B70: INV00000339 | C70: WSK Tanks Sdn Bhd | D70: 48172.5 | E70: -48172.5 | F70: 0 | N70: Kelnico Marketing | O70: INV2020/00000002 | R70: 480 | Y70: 480 | BT70: 480
B71: INV00000340 | C71: KT Profesional Fiber | D71: 2636.5 | E71: -2636.5 | F71: 0 | O71: INV2020/00000004 | R71: 2435 | Y71: 2435 | BT71: 2435
B72: INV00000341 | C72: Pandian Art Gallery Manufacturing | D72: 2849 | E72: -2849 | F72: 0 | O72: INV2020/00000008 | S72: 2098 | Y72: 2098 | BT72: 2098
B73: INV00000342 | C73: Pandian Art Gallery Manufacturing | D73: 4048 | E73: -4048 | F73: 0 | O73: INV2020/00000014 | T73: 2922 | Y73: 2922 | BT73: 2922
B74: INV00000343 | C74: Perniagaan Fibra Sahih | D74: 2237 | E74: -2237 | F74: 0 | O74: INV2020/00000015 | T74: 960 | Y74: 960 | BT74: 960
B75: INV00000344 | C75: Desuki Affela Empire Enterprise | D75: 3137.3 | E75: -3137.3 | F75: 0 | O75: INV2020/00000022 | T75: 1496 | Y75: 1496 | BT75: 1496
B76: INV00000345 | C76: WSK Tanks Sdn Bhd | D76: 10166.3 | E76: -10166.3 | F76: 0 | O76: INV2020/00000025 | U76: 1250 | Y76: 1250 | BT76: 1250
B77: INV00000346 | C77: KT Profesional Fiber | D77: 2570 | E77: -2570 | F77: 0 | O77: INV2020/00000026 | U77: 2458 | Y77: 2458 | BT77: 2458
B78: INV00000347 | C78: Yew Seng Gardening Supply Sdn Bhd | D78: 11480 | E78: -11480 | F78: 0 | O78: INV2020/00000028 | U78: 1977 | Y78: 1977 | BT78: 1977
B79: INV00000348 | C79: Megapower Service | D79: 3600 | E79: -3600 | F79: 0 | O79: INV2020/00000031 | U79: 1392 | Y79: 1392 | BT79: 1392
B80: INV00000349 | C80: Yew Seng Gardening Supply Sdn Bhd | D80: 395 | E80: -395 | F80: 0 | O80: INV2020/00000032 | U80: 1496 | Y80: 1496 | BT80: 1496
B81: INV00000350 | C81: JMC Steel Engineering Sdn Bhd | D81: 1960.2 | E81: -1960.2 | F81: 0 | O81: INV2020/00000037 | V81: 2458 | Y81: 2458 | BT81: 2458
B82: INV00000351 | C82: Siew Min Lorry Sdn Bhd | D82: 15677.2 | E82: -15677.2 | F82: 0 | O82: INV2020/00000041 | V82: 1645 | Y82: 1645 | BT82: 1645
B83: INV00000352 | C83: Kelnico Marketing | D83: 3004 | E83: -3004 | F83: 0 | O83: INV2020/00000046 | V83: 2458 | Y83: 2458 | BT83: 2458
B84: INV00000353 | C84: WSK Tanks Sdn Bhd | D84: 7590.5 | E84: -7590.5 | F84: 0 | O84: INV2020/00000049 | W84: 1954 | Y84: 1954 | BT84: 1954
B85: INV00000354 | C85: KT Profesional Fiber | D85: 2837 | E85: -2837 | F85: 0 | O85: INV2020/00000052 | W85: 1584 | Y85: 1584 | BT85: 1584
B86: INV00000355 | C86: WSK Tanks Sdn Bhd | D86: 250 | E86: -250 | F86: 0 | O86: INV2020/00000053 | W86: 520 | Y86: 520 | BT86: 520
B87: INV00000356 | C87: WSK Tanks Sdn Bhd | D87: 47685 | E87: -47685 | F87: 0 | O87: INV2020/00000059 | W87: 2424 | Y87: 2424 | BT87: 2424
B88: INV00000357 | C88: KT Profesional Fiber | D88: 3095 | E88: -3095 | F88: 0 | O88: INV2020/00000065 | X88: 2228 | Y88: 2228 | BT88: 2228
A89: 10 Total | D89: 186455.5 | E89: -186455.5 | F89: 0 | O89: INV2020/00000075 | AE89: 2866 | AJ89: 2866 | BT89: 2866
A90: 11 | B90: INV00000358 | C90: Siew Min Lorry Sdn Bhd | D90: 10824 | E90: -10824 | F90: 0 | O90: INV2020/00000082 | AF90: 1694 | AJ90: 1694 | BT90: 1694
B91: INV00000359 | C91: Yew Seng Gardening Supply Sdn Bhd | D91: 11260 | E91: -11260 | F91: 0 | O91: INV2019/00000001 | P91: 2973 | Q91: 2973 | BT91: 2973
B92: INV00000360 | C92: JMC Steel Engineering Sdn Bhd | D92: 4482.8 | E92: -4482.8 | F92: 0 | O92: INV00000099 | AH92: 520 | AJ92: 520 | BT92: 520
B93: INV00000361 | C93: WSK Tanks Sdn Bhd | D93: 403.8 | E93: -403.8 | F93: 0 | O93: INV00000104 | AI93: 2846 | AJ93: 2846 | BT93: 2846
B94: INV00000362 | C94: Cash - Big Jackfruit Trading | D94: 892.6 | E94: -892.6 | F94: 0 | O94: INV00000120 | AA94: 1870 | AJ94: 1870 | BT94: 1870
B95: INV00000363 | C95: SF Engineering Solution | D95: 1316 | E95: -1316 | F95: 0 | O95: INV00000143 | AB95: 6656 | AJ95: 6656 | BT95: 6656
B96: INV00000364 | C96: Hai Kee Hung Sdn Bhd | D96: 4373 | E96: -4373 | F96: 0 | O96: INV00000178 | AD96: 5591 | AJ96: 5591 | BT96: 5591
B97: INV00000365 | C97: KT Profesional Fiber | D97: 3094 | E97: -3094 | F97: 0 | O97: INV00000225 | AT97: 3232 | AW97: 3232 | BT97: 3232
B98: INV00000366 | C98: WSK Tanks Sdn Bhd | D98: 14886.5 | E98: -14886.5 | F98: 0 | O98: INV00000248 | AU98: 2488 | AW98: 2488 | BT98: 2488
B99: INV00000367 | C99: Transform Star Sdn Bhd | D99: 14564.6 | E99: -14564.6 | F99: 0 | O99: INV00000281 | AK99: 2356 | AW99: 2356 | BT99: 2356
B100: INV00000368 | C100: Desuki Affela Empire Enterprise | D100: 5283.2 | E100: -5283.2 | F100: 0 | O100: INV00000288 | AK100: 3232 | AW100: 3232 | BT100: 3232
B101: INV00000369 | C101: Desuki Affela Empire Enterprise | D101: 105 | E101: -105 | F101: 0 | O101: INV00000302 | AL101: 4092 | AW101: 4092 | BT101: 4092
...

Sheet Sales Qty_by product
A1: Year (Sales) | B1: 2024
A2: Period (Sales) | B2: 9
A4: Sum of Qty
A5: Product | B5: Total
A6: RA Butanox M50 (5Kg) | B6: 11
A7: RA Nor 3338W (220Kg) | B7: 2
A8: RE Frekote 770NC (1 Gallon) | B8: 1
A9: RH Bosny Wax (15kg) | B9: 1
A10: RM Resin 3317AW (220Kg) | B10: 2
A11: RM Pigment Super White (5Kg) | B11: 1
A12: RD Brush 3" (12Pc) | B12: 8
A13: RM Pigment Paste Smooth Cream M19 (25kg) | B13: 5
A14: RA Mepoxe (5kg) | B14: 13
A15: RA Resin 3338W (220kg) | B15: 12
A16: RM Resin 3338W (220kg) | B16: 1
A17: RM CSM 450 1860mm(W) (54kg) | B17: 2
... A32: Grand Total | B32: 353

Sheet Sales_by Inv No
E3: Values
A4: Year (Sales) | B4: Period (Sales) | C4: Invoice No | D4: Customer Name | E4: Sum of Sales Amount2 | F4: Sum of Collection | G4: Sum of Outstanding
A5: 2024 | B5: 8 | C5: INV00000934 | D5: Suntruck Sdn Bhd | E5: 8732.3 | F5: -8732.3 | G5: 0
C6: INV00000935 | D6: Welltech (M) Sdn Bhd | E6: 410 | F6: -410 | G6: 0
C7: INV00000936 | D7: Perniagaan Fibra Sahih | E7: 12250 | F7: -12250 | G7: 0
C8: INV00000937 | D8: Cash - Encik Razzak | E8: 2878 | F8: -2878 | G8: 0
C9: INV00000938 | D9: YL Professional Fiber Trading | E9: 2687.5 | F9: -2687.5 | G9: 0
C10: INV00000939 | D10: Yew Seng Gardening Supply Sdn Bhd | E10: 17177.6 | F10: -17177.6 | G10: 0
C11: INV00000940 | D11: Desuki Affela Empire Enterprise | E11: 2997.5 | G11: 2997.5
C12: INV00000941 | D12: Cash - Hamdan | E12: 1185 | F12: -1185 | G12: 0
C13: INV00000942 | D13: DOB Engineering Solutions | E13: 6210 | G13: 6210
C14: INV00000943 | D14: Welltech (M) Sdn Bhd | E14: 625 | F14: -625 | G14: 0
C15: INV00000944 | D15: Welltech (M) Sdn Bhd | E15: 26725 | F15: -26725 | G15: 0
C16: INV00000945 | D16: Megapower Service | E16: 2143 | F16: -2143 | G16: 0
C17: INV00000946 | D17: Pandian Art Gallery Manufacturing | E17: 2322 | F17: -2322 | G17: 0
C18: INV00000947 | D18: DOB Engineering Solutions | E18: 4195 | G18: 4195
C19: INV00000948 | D19: DOB Engineering Solutions | E19: 110 | G19: 110
C20: INV00000949 | D20: Welltech (M) Sdn Bhd | E20: 1000 | F20: -1000 | G20: 0
C21: INV00000950 | D21: DOB Engineering Solutions | E21: 250 | G21: 250
C22: INV00000951 | D22: Desuki Affela Empire Enterprise | E22: 1880 | G22: 1880
C23: INV00000952 | D23: DOB Engineering Solutions | E23: 180 | G23: 180
C24: INV00000953 | D24: Welltech (M) Sdn Bhd | E24: 125 | F24: -125 | G24: 0
C25: INV00000954 | D25: Welltech (M) Sdn Bhd | E25: 4734 | F25: -4734 | G25: 0
C26: INV00000955 | D26: DOB Engineering Solutions | E26: 175 | G26: 175
C27: INV00000956 | D27: Welltech (M) Sdn Bhd | E27: 187.5 | F27: -187.5 | G27: 0
C28: INV00000957 | D28: Welltech (M) Sdn Bhd | E28: 9269 | F28: -9269 | G28: 0
C29: INV00000958 | D29: Transform Star Sdn Bhd | E29: 8026.4 | G29: 8026.4
C30: INV00000959 | D30: Yew Seng Gardening Supply Sdn Bhd | E30: 881 | F30: -881 | G30: 0
C31: INV00000960 | D31: IK Fibre Glass Enterprise | E31: 207 | F31: -207 | G31: 0
C32: INV00000961 | D32: Desuki Affela Empire Enterprise | E32: 2772.5 | G32: 2772.5
C33: INV00000962 | D33: Welltech (M) Sdn Bhd | E33: 250 | F33: -250 | G33: 0
C34: INV00000963 | D34: Welltech (M) Sdn Bhd | E34: 9908 | F34: -9908 | G34: 0
C35: INV00000964 | D35: Yew Seng Gardening Supply Sdn Bhd | E35: 2450 | F35: -2450 | G35: 0
B36: 8 Total | E36: 132943.3 | F36: -106146.9 | G36: 26796.4
A37: 2024 Total | E37: 132943.3 | F37: -106146.9 | G37: 26796.4
A38: Grand Total | E38: 132943.3 | F38: -106146.9 | G38: 26796.4
